[
  {
    "id": 1,
    "firstname": "Livvyy",
    "last_name": "Deppen",
    "email": "ldeppen0@bloglines.com",
    "address": "48 Dovetail Circle",
    "actions": ""
  },
  {
    "id": 2,
    "firstname": "Shirlene",
    "last_name": "Casassa",
    "email": "scasassa1@mozilla.org",
    "address": "86032 Continental Crossing",
    "actions": ""
  },
  {
    "id": 3,
    "firstname": "Renard",
    "last_name": "Sprott",
    "email": "rsprott2@cnbc.com",
    "address": "4637 West Circle",
    "actions": ""
  },
  {
    "id": 4,
    "firstname": "Irma",
    "last_name": "Westnedge",
    "email": "iwestnedge3@yale.edu",
    "address": "856 Lotheville Circle",
    "actions": ""
  },
  {
    "id": 5,
    "firstname": "Evey",
    "last_name": "Pollok",
    "email": "epollok4@narod.ru",
    "address": "734 Pawling Point",
    "actions": ""
  },
  {
    "id": 6,
    "firstname": "Alasdair",
    "last_name": "Devons",
    "email": "adevons5@baidu.com",
    "address": "794 Dahle Center",
    "actions": ""
  },
  {
    "id": 7,
    "firstname": "Prentiss",
    "last_name": "Troop",
    "email": "ptroop6@a8.net",
    "address": "1 Carberry Court",
    "actions": ""
  },
  {
    "id": 8,
    "firstname": "Ross",
    "last_name": "Cuddy",
    "email": "rcuddy7@over-blog.com",
    "address": "69 Sommers Hill",
    "actions": ""
  },
  {
    "id": 9,
    "firstname": "Micaela",
    "last_name": "Fildes",
    "email": "mfildes8@state.gov",
    "address": "58837 Green Road",
    "actions": ""
  },
  {
    "id": 10,
    "firstname": "Romonda",
    "last_name": "Wegner",
    "email": "rwegner9@symantec.com",
    "address": "982 Manley Crossing",
    "actions": ""
  },
  {
    "id": 11,
    "firstname": "Upton",
    "last_name": "Desaur",
    "email": "udesaura@mapy.cz",
    "address": "8 Cardinal Street",
    "actions": ""
  },
  {
    "id": 12,
    "firstname": "Tricia",
    "last_name": "Trollope",
    "email": "ttrollopeb@livejournal.com",
    "address": "1323 Ruskin Street",
    "actions": ""
  },
  {
    "id": 13,
    "firstname": "Fania",
    "last_name": "Darbishire",
    "email": "fdarbishirec@ifeng.com",
    "address": "575 Grim Drive",
    "actions": ""
  },
  {
    "id": 14,
    "firstname": "Donelle",
    "last_name": "Conibeer",
    "email": "dconibeerd@godaddy.com",
    "address": "3465 Jenna Pass",
    "actions": ""
  },
  {
    "id": 15,
    "firstname": "Andromache",
    "last_name": "Toulson",
    "email": "atoulsone@hubpages.com",
    "address": "696 Hollow Ridge Point",
    "actions": ""
  },
  {
    "id": 16,
    "firstname": "Camilla",
    "last_name": "Showen",
    "email": "cshowenf@artisteer.com",
    "address": "04 Sloan Court",
    "actions": ""
  },
  {
    "id": 17,
    "firstname": "Delilah",
    "last_name": "Kassidy",
    "email": "dkassidyg@nih.gov",
    "address": "58981 North Court",
    "actions": ""
  },
  {
    "id": 18,
    "firstname": "Jolyn",
    "last_name": "Strathern",
    "email": "jstrathernh@drupal.org",
    "address": "10391 Ridge Oak Alley",
    "actions": ""
  },
  {
    "id": 19,
    "firstname": "Jilli",
    "last_name": "Cuttles",
    "email": "jcuttlesi@squidoo.com",
    "address": "17044 Moland Court",
    "actions": ""
  },
  {
    "id": 20,
    "firstname": "Jamal",
    "last_name": "Parlot",
    "email": "jparlotj@fastcompany.com",
    "address": "29901 Mendota Trail",
    "actions": ""
  },
  {
    "id": 21,
    "firstname": "Adam",
    "last_name": "Skep",
    "email": "askepk@mapquest.com",
    "address": "0458 Trailsway Lane",
    "actions": ""
  },
  {
    "id": 22,
    "firstname": "Terese",
    "last_name": "Northrop",
    "email": "tnorthropl@deviantart.com",
    "address": "6 Nova Place",
    "actions": ""
  },
  {
    "id": 23,
    "firstname": "Alvira",
    "last_name": "Collard",
    "email": "acollardm@geocities.com",
    "address": "3 Prentice Circle",
    "actions": ""
  },
  {
    "id": 24,
    "firstname": "Cristi",
    "last_name": "Dearnly",
    "email": "cdearnlyn@columbia.edu",
    "address": "382 Pankratz Circle",
    "actions": ""
  },
  {
    "id": 25,
    "firstname": "Harold",
    "last_name": "Crickett",
    "email": "hcricketto@epa.gov",
    "address": "08650 Canary Court",
    "actions": ""
  },
  {
    "id": 26,
    "firstname": "Tobit",
    "last_name": "Costar",
    "email": "tcostarp@ibm.com",
    "address": "63 Westport Crossing",
    "actions": ""
  },
  {
    "id": 27,
    "firstname": "Rand",
    "last_name": "Jagels",
    "email": "rjagelsq@ocn.ne.jp",
    "address": "7803 Oneill Plaza",
    "actions": ""
  },
  {
    "id": 28,
    "firstname": "Valentia",
    "last_name": "Van T'Hoog",
    "email": "vvanthoogr@china.com.cn",
    "address": "68 Bunker Hill Circle",
    "actions": ""
  },
  {
    "id": 29,
    "firstname": "Mark",
    "last_name": "Hartnell",
    "email": "mhartnells@google.com.hk",
    "address": "204 Welch Parkway",
    "actions": ""
  },
  {
    "id": 30,
    "firstname": "Liz",
    "last_name": "Cathro",
    "email": "lcathrot@qq.com",
    "address": "9967 Kenwood Street",
    "actions": ""
  },
  {
    "id": 31,
    "firstname": "Ade",
    "last_name": "Viall",
    "email": "aviallu@163.com",
    "address": "91730 Glacier Hill Plaza",
    "actions": ""
  },
  {
    "id": 32,
    "firstname": "Tara",
    "last_name": "Summers",
    "email": "tsummersv@biglobe.ne.jp",
    "address": "5759 Elka Crossing",
    "actions": ""
  },
  {
    "id": 33,
    "firstname": "Ines",
    "last_name": "Maxfield",
    "email": "imaxfieldw@163.com",
    "address": "55730 Manufacturers Lane",
    "actions": ""
  },
  {
    "id": 34,
    "firstname": "Merci",
    "last_name": "Paulot",
    "email": "mpaulotx@trellian.com",
    "address": "784 Spenser Pass",
    "actions": ""
  },
  {
    "id": 35,
    "firstname": "Min",
    "last_name": "Birkmyre",
    "email": "mbirkmyrey@pagesperso-orange.fr",
    "address": "53 Carey Terrace",
    "actions": ""
  },
  {
    "id": 36,
    "firstname": "Leonora",
    "last_name": "Denford",
    "email": "ldenfordz@samsung.com",
    "address": "6 Canary Place",
    "actions": ""
  },
  {
    "id": 37,
    "firstname": "Leland",
    "last_name": "Ygou",
    "email": "lygou10@nba.com",
    "address": "37124 Oak Valley Circle",
    "actions": ""
  },
  {
    "id": 38,
    "firstname": "Noelle",
    "last_name": "Spieght",
    "email": "nspieght11@businessweek.com",
    "address": "6790 Messerschmidt Circle",
    "actions": ""
  },
  {
    "id": 39,
    "firstname": "Beatrix",
    "last_name": "Cloney",
    "email": "bcloney12@feedburner.com",
    "address": "02508 Crownhardt Alley",
    "actions": ""
  },
  {
    "id": 40,
    "firstname": "Noellyn",
    "last_name": "Crutchley",
    "email": "ncrutchley13@pen.io",
    "address": "40866 Artisan Drive",
    "actions": ""
  },
  {
    "id": 41,
    "firstname": "Lolly",
    "last_name": "Whewill",
    "email": "lwhewill14@gov.uk",
    "address": "13 Maple Wood Lane",
    "actions": ""
  },
  {
    "id": 42,
    "firstname": "Fan",
    "last_name": "Inglish",
    "email": "finglish15@com.com",
    "address": "6 Bayside Way",
    "actions": ""
  },
  {
    "id": 43,
    "firstname": "Ashley",
    "last_name": "Rotchell",
    "email": "arotchell16@theatlantic.com",
    "address": "812 Green Ridge Pass",
    "actions": ""
  },
  {
    "id": 44,
    "firstname": "Gavan",
    "last_name": "Dugald",
    "email": "gdugald17@theglobeandmail.com",
    "address": "770 Forster Park",
    "actions": ""
  },
  {
    "id": 45,
    "firstname": "Arne",
    "last_name": "Parnham",
    "email": "aparnham18@seesaa.net",
    "address": "12290 Oak Lane",
    "actions": ""
  },
  {
    "id": 46,
    "firstname": "Sidnee",
    "last_name": "Westwick",
    "email": "swestwick19@flickr.com",
    "address": "55279 Hooker Park",
    "actions": ""
  },
  {
    "id": 47,
    "firstname": "Nedi",
    "last_name": "Gorbell",
    "email": "ngorbell1a@pen.io",
    "address": "9 Garrison Road",
    "actions": ""
  },
  {
    "id": 48,
    "firstname": "Tobe",
    "last_name": "Dechelette",
    "email": "tdechelette1b@sphinn.com",
    "address": "894 Coleman Road",
    "actions": ""
  },
  {
    "id": 49,
    "firstname": "Blondell",
    "last_name": "Shane",
    "email": "bshane1c@cdbaby.com",
    "address": "2 Division Terrace",
    "actions": ""
  },
  {
    "id": 50,
    "firstname": "Odelinda",
    "last_name": "Tarzey",
    "email": "otarzey1d@privacy.gov.au",
    "address": "139 Weeping Birch Way",
    "actions": ""
  },
  {
    "id": 51,
    "firstname": "Lorenzo",
    "last_name": "Farnie",
    "email": "lfarnie1e@ustream.tv",
    "address": "9225 Northport Center",
    "actions": ""
  },
  {
    "id": 52,
    "firstname": "Bonni",
    "last_name": "Getty",
    "email": "bgetty1f@qq.com",
    "address": "9196 Division Way",
    "actions": ""
  },
  {
    "id": 53,
    "firstname": "Vonnie",
    "last_name": "Itzcovichch",
    "email": "vitzcovichch1g@dyndns.org",
    "address": "458 Swallow Court",
    "actions": ""
  },
  {
    "id": 54,
    "firstname": "Hubert",
    "last_name": "Alsopp",
    "email": "halsopp1h@parallels.com",
    "address": "0361 Anhalt Parkway",
    "actions": ""
  },
  {
    "id": 55,
    "firstname": "Katti",
    "last_name": "Filoniere",
    "email": "kfiloniere1i@ocn.ne.jp",
    "address": "64 Brickson Park Court",
    "actions": ""
  },
  {
    "id": 56,
    "firstname": "Rock",
    "last_name": "Pakes",
    "email": "rpakes1j@oracle.com",
    "address": "52 Namekagon Drive",
    "actions": ""
  },
  {
    "id": 57,
    "firstname": "Mina",
    "last_name": "Brown",
    "email": "mbrown1k@webnode.com",
    "address": "8439 School Plaza",
    "actions": ""
  },
  {
    "id": 58,
    "firstname": "Bonnibelle",
    "last_name": "Marcoolyn",
    "email": "bmarcoolyn1l@icio.us",
    "address": "9852 Comanche Way",
    "actions": ""
  },
  {
    "id": 59,
    "firstname": "Agata",
    "last_name": "MacConnechie",
    "email": "amacconnechie1m@posterous.com",
    "address": "494 Grasskamp Center",
    "actions": ""
  },
  {
    "id": 60,
    "firstname": "Izak",
    "last_name": "Shapira",
    "email": "ishapira1n@cnn.com",
    "address": "973 Paget Drive",
    "actions": ""
  },
  {
    "id": 61,
    "firstname": "Georgetta",
    "last_name": "Pigney",
    "email": "gpigney1o@geocities.com",
    "address": "8150 Armistice Place",
    "actions": ""
  },
  {
    "id": 62,
    "firstname": "Geralda",
    "last_name": "Pulfer",
    "email": "gpulfer1p@ox.ac.uk",
    "address": "3 Straubel Crossing",
    "actions": ""
  },
  {
    "id": 63,
    "firstname": "Claudianus",
    "last_name": "Bullas",
    "email": "cbullas1q@examiner.com",
    "address": "3 5th Circle",
    "actions": ""
  },
  {
    "id": 64,
    "firstname": "Nikolaos",
    "last_name": "Coraini",
    "email": "ncoraini1r@exblog.jp",
    "address": "56 Arrowood Parkway",
    "actions": ""
  },
  {
    "id": 65,
    "firstname": "Emilie",
    "last_name": "Gagie",
    "email": "egagie1s@psu.edu",
    "address": "139 Sommers Trail",
    "actions": ""
  },
  {
    "id": 66,
    "firstname": "Barty",
    "last_name": "Fugere",
    "email": "bfugere1t@vk.com",
    "address": "9 Golf Course Circle",
    "actions": ""
  },
  {
    "id": 67,
    "firstname": "Isadora",
    "last_name": "Meech",
    "email": "imeech1u@microsoft.com",
    "address": "0 Northridge Park",
    "actions": ""
  },
  {
    "id": 68,
    "firstname": "Torre",
    "last_name": "Blees",
    "email": "tblees1v@amazon.de",
    "address": "447 Old Shore Point",
    "actions": ""
  },
  {
    "id": 69,
    "firstname": "Verge",
    "last_name": "Chasle",
    "email": "vchasle1w@etsy.com",
    "address": "8940 Daystar Place",
    "actions": ""
  },
  {
    "id": 70,
    "firstname": "Dell",
    "last_name": "Jellicorse",
    "email": "djellicorse1x@ameblo.jp",
    "address": "948 Algoma Parkway",
    "actions": ""
  },
  {
    "id": 71,
    "firstname": "Janine",
    "last_name": "Nurdin",
    "email": "jnurdin1y@multiply.com",
    "address": "5 Garrison Point",
    "actions": ""
  },
  {
    "id": 72,
    "firstname": "Isidor",
    "last_name": "Godier",
    "email": "igodier1z@imgur.com",
    "address": "6965 Hayes Terrace",
    "actions": ""
  },
  {
    "id": 73,
    "firstname": "Jannelle",
    "last_name": "Solley",
    "email": "jsolley20@imageshack.us",
    "address": "47 Calypso Plaza",
    "actions": ""
  },
  {
    "id": 74,
    "firstname": "Lucian",
    "last_name": "Feeley",
    "email": "lfeeley21@sina.com.cn",
    "address": "429 Becker Drive",
    "actions": ""
  },
  {
    "id": 75,
    "firstname": "Mandel",
    "last_name": "Rodman",
    "email": "mrodman22@indiegogo.com",
    "address": "0363 Stephen Way",
    "actions": ""
  },
  {
    "id": 76,
    "firstname": "Miran",
    "last_name": "Woodrooffe",
    "email": "mwoodrooffe23@scientificamerican.com",
    "address": "923 Heath Junction",
    "actions": ""
  },
  {
    "id": 77,
    "firstname": "Talya",
    "last_name": "Andreasen",
    "email": "tandreasen24@mashable.com",
    "address": "2 Melrose Road",
    "actions": ""
  },
  {
    "id": 78,
    "firstname": "Mable",
    "last_name": "Coxon",
    "email": "mcoxon25@google.ca",
    "address": "6 Portage Junction",
    "actions": ""
  },
  {
    "id": 79,
    "firstname": "Donetta",
    "last_name": "Veevers",
    "email": "dveevers26@deviantart.com",
    "address": "35 Morningstar Drive",
    "actions": ""
  },
  {
    "id": 80,
    "firstname": "Van",
    "last_name": "Colyer",
    "email": "vcolyer27@ifeng.com",
    "address": "662 Bobwhite Alley",
    "actions": ""
  },
  {
    "id": 81,
    "firstname": "Mattie",
    "last_name": "Nutton",
    "email": "mnutton28@apache.org",
    "address": "48884 Ronald Regan Center",
    "actions": ""
  },
  {
    "id": 82,
    "firstname": "Cash",
    "last_name": "Pacitti",
    "email": "cpacitti29@ucoz.ru",
    "address": "1 Farragut Pass",
    "actions": ""
  },
  {
    "id": 83,
    "firstname": "Amie",
    "last_name": "Filchakov",
    "email": "afilchakov2a@angelfire.com",
    "address": "9 Mallard Park",
    "actions": ""
  },
  {
    "id": 84,
    "firstname": "Nicolas",
    "last_name": "Benoist",
    "email": "nbenoist2b@bizjournals.com",
    "address": "9 Southridge Avenue",
    "actions": ""
  },
  {
    "id": 85,
    "firstname": "Antoinette",
    "last_name": "Maylor",
    "email": "amaylor2c@jimdo.com",
    "address": "260 Barby Plaza",
    "actions": ""
  },
  {
    "id": 86,
    "firstname": "Ketty",
    "last_name": "Kun",
    "email": "kkun2d@unblog.fr",
    "address": "318 Washington Drive",
    "actions": ""
  },
  {
    "id": 87,
    "firstname": "Jacquetta",
    "last_name": "Scough",
    "email": "jscough2e@unblog.fr",
    "address": "05914 Green Ridge Junction",
    "actions": ""
  },
  {
    "id": 88,
    "firstname": "Lidia",
    "last_name": "Pahler",
    "email": "lpahler2f@wordpress.com",
    "address": "41 Browning Street",
    "actions": ""
  },
  {
    "id": 89,
    "firstname": "Adina",
    "last_name": "Tippler",
    "email": "atippler2g@stanford.edu",
    "address": "199 Anhalt Way",
    "actions": ""
  },
  {
    "id": 90,
    "firstname": "Llywellyn",
    "last_name": "Marcinkowski",
    "email": "lmarcinkowski2h@eventbrite.com",
    "address": "187 Gerald Place",
    "actions": ""
  },
  {
    "id": 91,
    "firstname": "Roxy",
    "last_name": "Fenech",
    "email": "rfenech2i@ucsd.edu",
    "address": "650 Mendota Pass",
    "actions": ""
  },
  {
    "id": 92,
    "firstname": "Zabrina",
    "last_name": "Gussie",
    "email": "zgussie2j@gov.uk",
    "address": "64716 Spenser Lane",
    "actions": ""
  },
  {
    "id": 93,
    "firstname": "Stephine",
    "last_name": "Beevor",
    "email": "sbeevor2k@ow.ly",
    "address": "870 Beilfuss Pass",
    "actions": ""
  },
  {
    "id": 94,
    "firstname": "Fairleigh",
    "last_name": "Bartholomaus",
    "email": "fbartholomaus2l@ca.gov",
    "address": "77 Mayfield Road",
    "actions": ""
  },
  {
    "id": 95,
    "firstname": "Isa",
    "last_name": "Cardello",
    "email": "icardello2m@networksolutions.com",
    "address": "615 Village Pass",
    "actions": ""
  },
  {
    "id": 96,
    "firstname": "Rafaello",
    "last_name": "Kevane",
    "email": "rkevane2n@liveinternet.ru",
    "address": "9700 Clyde Gallagher Plaza",
    "actions": ""
  },
  {
    "id": 97,
    "firstname": "Freddy",
    "last_name": "Vogt",
    "email": "fvogt2o@purevolume.com",
    "address": "85 Dayton Avenue",
    "actions": ""
  },
  {
    "id": 98,
    "firstname": "Tedd",
    "last_name": "Alphonso",
    "email": "talphonso2p@php.net",
    "address": "0 Heath Plaza",
    "actions": ""
  },
  {
    "id": 99,
    "firstname": "Robbie",
    "last_name": "Truett",
    "email": "rtruett2q@redcross.org",
    "address": "8 Helena Street",
    "actions": ""
  },
  {
    "id": 100,
    "firstname": "Iorgos",
    "last_name": "McSparran",
    "email": "imcsparran2r@un.org",
    "address": "9 Sunfield Way",
    "actions": ""
  },
  {
    "id": 101,
    "firstname": "Reynard",
    "last_name": "Jakubovicz",
    "email": "rjakubovicz2s@wikispaces.com",
    "address": "708 Grover Trail",
    "actions": ""
  },
  {
    "id": 102,
    "firstname": "Inglebert",
    "last_name": "Esome",
    "email": "iesome2t@jugem.jp",
    "address": "4 Nova Parkway",
    "actions": ""
  },
  {
    "id": 103,
    "firstname": "Catharina",
    "last_name": "Reboulet",
    "email": "creboulet2u@cafepress.com",
    "address": "85 Hauk Circle",
    "actions": ""
  },
  {
    "id": 104,
    "firstname": "Andrea",
    "last_name": "Levinge",
    "email": "alevinge2v@yahoo.co.jp",
    "address": "115 Springview Alley",
    "actions": ""
  },
  {
    "id": 105,
    "firstname": "Lenora",
    "last_name": "Andreazzi",
    "email": "landreazzi2w@patch.com",
    "address": "5810 Commercial Circle",
    "actions": ""
  },
  {
    "id": 106,
    "firstname": "Cleo",
    "last_name": "Snashall",
    "email": "csnashall2x@marketwatch.com",
    "address": "2544 Mcbride Place",
    "actions": ""
  },
  {
    "id": 107,
    "firstname": "Lisa",
    "last_name": "Burditt",
    "email": "lburditt2y@cornell.edu",
    "address": "28121 Londonderry Park",
    "actions": ""
  },
  {
    "id": 108,
    "firstname": "Bendix",
    "last_name": "Garioch",
    "email": "bgarioch2z@jalbum.net",
    "address": "8620 8th Drive",
    "actions": ""
  },
  {
    "id": 109,
    "firstname": "Michel",
    "last_name": "Demchen",
    "email": "mdemchen30@t-online.de",
    "address": "02052 Reindahl Parkway",
    "actions": ""
  },
  {
    "id": 110,
    "firstname": "Elsey",
    "last_name": "Lehrahan",
    "email": "elehrahan31@amazon.co.jp",
    "address": "6798 Goodland Center",
    "actions": ""
  },
  {
    "id": 111,
    "firstname": "Fionna",
    "last_name": "Pollington",
    "email": "fpollington32@tmall.com",
    "address": "54 Riverside Place",
    "actions": ""
  },
  {
    "id": 112,
    "firstname": "Kevin",
    "last_name": "Abbyss",
    "email": "kabbyss33@army.mil",
    "address": "3 Loftsgordon Court",
    "actions": ""
  },
  {
    "id": 113,
    "firstname": "Chrissie",
    "last_name": "Hearty",
    "email": "chearty34@youtube.com",
    "address": "844 Vermont Place",
    "actions": ""
  },
  {
    "id": 114,
    "firstname": "Kariotta",
    "last_name": "Liebmann",
    "email": "kliebmann35@ox.ac.uk",
    "address": "9 Green Center",
    "actions": ""
  },
  {
    "id": 115,
    "firstname": "Burk",
    "last_name": "Kilbee",
    "email": "bkilbee36@illinois.edu",
    "address": "2247 Hagan Parkway",
    "actions": ""
  },
  {
    "id": 116,
    "firstname": "Osmund",
    "last_name": "Emerson",
    "email": "oemerson37@delicious.com",
    "address": "52 International Drive",
    "actions": ""
  },
  {
    "id": 117,
    "firstname": "Sacha",
    "last_name": "Overshott",
    "email": "sovershott38@ftc.gov",
    "address": "62840 Del Mar Hill",
    "actions": ""
  },
  {
    "id": 118,
    "firstname": "Elroy",
    "last_name": "Cantle",
    "email": "ecantle39@unicef.org",
    "address": "8 Pierstorff Pass",
    "actions": ""
  },
  {
    "id": 119,
    "firstname": "Maribeth",
    "last_name": "Raffan",
    "email": "mraffan3a@narod.ru",
    "address": "1 Saint Paul Park",
    "actions": ""
  },
  {
    "id": 120,
    "firstname": "Parrnell",
    "last_name": "Gush",
    "email": "pgush3b@webs.com",
    "address": "8 Service Alley",
    "actions": ""
  },
  {
    "id": 121,
    "firstname": "Agnese",
    "last_name": "Casburn",
    "email": "acasburn3c@gizmodo.com",
    "address": "49 Rowland Center",
    "actions": ""
  },
  {
    "id": 122,
    "firstname": "Jacinta",
    "last_name": "Quilligan",
    "email": "jquilligan3d@creativecommons.org",
    "address": "136 Dorton Crossing",
    "actions": ""
  },
  {
    "id": 123,
    "firstname": "Zsazsa",
    "last_name": "Ruggs",
    "email": "zruggs3e@geocities.jp",
    "address": "17 Autumn Leaf Avenue",
    "actions": ""
  },
  {
    "id": 124,
    "firstname": "Aguste",
    "last_name": "Anstee",
    "email": "aanstee3f@surveymonkey.com",
    "address": "962 Toban Terrace",
    "actions": ""
  },
  {
    "id": 125,
    "firstname": "Keelby",
    "last_name": "Keirl",
    "email": "kkeirl3g@ebay.co.uk",
    "address": "6 Sage Center",
    "actions": ""
  },
  {
    "id": 126,
    "firstname": "Leticia",
    "last_name": "Costy",
    "email": "lcosty3h@craigslist.org",
    "address": "799 Blue Bill Park Drive",
    "actions": ""
  },
  {
    "id": 127,
    "firstname": "Rachael",
    "last_name": "Kuscha",
    "email": "rkuscha3i@google.com",
    "address": "38379 Dakota Road",
    "actions": ""
  },
  {
    "id": 128,
    "firstname": "Babita",
    "last_name": "Redmore",
    "email": "bredmore3j@live.com",
    "address": "01130 Moland Avenue",
    "actions": ""
  },
  {
    "id": 129,
    "firstname": "Jefferson",
    "last_name": "Triner",
    "email": "jtriner3k@baidu.com",
    "address": "77252 Shopko Terrace",
    "actions": ""
  },
  {
    "id": 130,
    "firstname": "Ibby",
    "last_name": "Caddens",
    "email": "icaddens3l@friendfeed.com",
    "address": "57243 Shoshone Parkway",
    "actions": ""
  },
  {
    "id": 131,
    "firstname": "Juanita",
    "last_name": "Causier",
    "email": "jcausier3m@dailymail.co.uk",
    "address": "3094 Melby Lane",
    "actions": ""
  },
  {
    "id": 132,
    "firstname": "Dougy",
    "last_name": "De Vile",
    "email": "ddevile3n@vimeo.com",
    "address": "56330 Pine View Avenue",
    "actions": ""
  },
  {
    "id": 133,
    "firstname": "Tove",
    "last_name": "Cosker",
    "email": "tcosker3o@studiopress.com",
    "address": "581 Hoard Lane",
    "actions": ""
  },
  {
    "id": 134,
    "firstname": "Catharine",
    "last_name": "Blastock",
    "email": "cblastock3p@npr.org",
    "address": "4 Sauthoff Way",
    "actions": ""
  },
  {
    "id": 135,
    "firstname": "Lyon",
    "last_name": "Rushman",
    "email": "lrushman3q@indiegogo.com",
    "address": "97 Packers Avenue",
    "actions": ""
  },
  {
    "id": 136,
    "firstname": "Arne",
    "last_name": "Danilewicz",
    "email": "adanilewicz3r@nhs.uk",
    "address": "8 Briar Crest Crossing",
    "actions": ""
  },
  {
    "id": 137,
    "firstname": "Gabey",
    "last_name": "MacGilmartin",
    "email": "gmacgilmartin3s@hibu.com",
    "address": "57 Fordem Crossing",
    "actions": ""
  },
  {
    "id": 138,
    "firstname": "Delinda",
    "last_name": "Ropkes",
    "email": "dropkes3t@wufoo.com",
    "address": "37 Schmedeman Plaza",
    "actions": ""
  },
  {
    "id": 139,
    "firstname": "Cecilius",
    "last_name": "Ringrose",
    "email": "cringrose3u@cmu.edu",
    "address": "578 Lawn Trail",
    "actions": ""
  },
  {
    "id": 140,
    "firstname": "Kata",
    "last_name": "Abrahmovici",
    "email": "kabrahmovici3v@google.com.au",
    "address": "87029 Kropf Circle",
    "actions": ""
  },
  {
    "id": 141,
    "firstname": "Gabbi",
    "last_name": "Letixier",
    "email": "gletixier3w@foxnews.com",
    "address": "4062 Monterey Park",
    "actions": ""
  },
  {
    "id": 142,
    "firstname": "Shelby",
    "last_name": "Wyrill",
    "email": "swyrill3x@si.edu",
    "address": "7 Northview Parkway",
    "actions": ""
  },
  {
    "id": 143,
    "firstname": "Addison",
    "last_name": "Durrell",
    "email": "adurrell3y@baidu.com",
    "address": "562 David Park",
    "actions": ""
  },
  {
    "id": 144,
    "firstname": "Jackquelin",
    "last_name": "Lorand",
    "email": "jlorand3z@nyu.edu",
    "address": "53 Logan Plaza",
    "actions": ""
  },
  {
    "id": 145,
    "firstname": "Tami",
    "last_name": "Greader",
    "email": "tgreader40@github.io",
    "address": "39 Del Sol Way",
    "actions": ""
  },
  {
    "id": 146,
    "firstname": "Ian",
    "last_name": "Bris",
    "email": "ibris41@wired.com",
    "address": "8 Barnett Trail",
    "actions": ""
  },
  {
    "id": 147,
    "firstname": "Rickie",
    "last_name": "Allday",
    "email": "rallday42@apple.com",
    "address": "07 Buena Vista Court",
    "actions": ""
  },
  {
    "id": 148,
    "firstname": "Ermentrude",
    "last_name": "Gelly",
    "email": "egelly43@miitbeian.gov.cn",
    "address": "58933 Moland Crossing",
    "actions": ""
  },
  {
    "id": 149,
    "firstname": "Josephine",
    "last_name": "Petrelli",
    "email": "jpetrelli44@wikipedia.org",
    "address": "14 Commercial Avenue",
    "actions": ""
  },
  {
    "id": 150,
    "firstname": "Coriss",
    "last_name": "Etridge",
    "email": "cetridge45@yandex.ru",
    "address": "852 Novick Avenue",
    "actions": ""
  },
  {
    "id": 151,
    "firstname": "Lambert",
    "last_name": "Goodliff",
    "email": "lgoodliff46@networksolutions.com",
    "address": "6747 Raven Lane",
    "actions": ""
  },
  {
    "id": 152,
    "firstname": "Deane",
    "last_name": "Burston",
    "email": "dburston47@blog.com",
    "address": "4401 Kennedy Crossing",
    "actions": ""
  },
  {
    "id": 153,
    "firstname": "Arden",
    "last_name": "Tabard",
    "email": "atabard48@acquirethisname.com",
    "address": "99 Melrose Park",
    "actions": ""
  },
  {
    "id": 154,
    "firstname": "Elfie",
    "last_name": "Moodie",
    "email": "emoodie49@acquirethisname.com",
    "address": "5217 Thackeray Point",
    "actions": ""
  },
  {
    "id": 155,
    "firstname": "Rodrick",
    "last_name": "Beeke",
    "email": "rbeeke4a@cmu.edu",
    "address": "1492 Anniversary Junction",
    "actions": ""
  },
  {
    "id": 156,
    "firstname": "Webb",
    "last_name": "Sporrij",
    "email": "wsporrij4b@hao123.com",
    "address": "3 Drewry Way",
    "actions": ""
  },
  {
    "id": 157,
    "firstname": "Zorana",
    "last_name": "Mehmet",
    "email": "zmehmet4c@trellian.com",
    "address": "11193 Graceland Circle",
    "actions": ""
  },
  {
    "id": 158,
    "firstname": "Domingo",
    "last_name": "Maxfield",
    "email": "dmaxfield4d@e-recht24.de",
    "address": "2 Westport Terrace",
    "actions": ""
  },
  {
    "id": 159,
    "firstname": "Agathe",
    "last_name": "Kryszka",
    "email": "akryszka4e@fotki.com",
    "address": "173 Grover Crossing",
    "actions": ""
  },
  {
    "id": 160,
    "firstname": "Franky",
    "last_name": "Godfree",
    "email": "fgodfree4f@clickbank.net",
    "address": "7547 Blue Bill Park Center",
    "actions": ""
  },
  {
    "id": 161,
    "firstname": "Silvester",
    "last_name": "McGoon",
    "email": "smcgoon4g@github.com",
    "address": "09 Lien Way",
    "actions": ""
  },
  {
    "id": 162,
    "firstname": "Cosimo",
    "last_name": "Belch",
    "email": "cbelch4h@desdev.cn",
    "address": "70278 Coleman Lane",
    "actions": ""
  },
  {
    "id": 163,
    "firstname": "Tori",
    "last_name": "Messier",
    "email": "tmessier4i@cisco.com",
    "address": "8186 Londonderry Point",
    "actions": ""
  },
  {
    "id": 164,
    "firstname": "Robby",
    "last_name": "Do Rosario",
    "email": "rdorosario4j@1und1.de",
    "address": "326 Jackson Hill",
    "actions": ""
  },
  {
    "id": 165,
    "firstname": "Niles",
    "last_name": "Joseff",
    "email": "njoseff4k@squarespace.com",
    "address": "34838 North Street",
    "actions": ""
  },
  {
    "id": 166,
    "firstname": "Bernadine",
    "last_name": "Carthy",
    "email": "bcarthy4l@qq.com",
    "address": "03 Packers Hill",
    "actions": ""
  },
  {
    "id": 167,
    "firstname": "Filia",
    "last_name": "Gladhill",
    "email": "fgladhill4m@fotki.com",
    "address": "18 Vidon Drive",
    "actions": ""
  },
  {
    "id": 168,
    "firstname": "Evie",
    "last_name": "Kadwallider",
    "email": "ekadwallider4n@trellian.com",
    "address": "47 Loomis Circle",
    "actions": ""
  },
  {
    "id": 169,
    "firstname": "Orly",
    "last_name": "Spaight",
    "email": "ospaight4o@java.com",
    "address": "8 Carberry Junction",
    "actions": ""
  },
  {
    "id": 170,
    "firstname": "Shawna",
    "last_name": "McGoogan",
    "email": "smcgoogan4p@yolasite.com",
    "address": "69886 Kipling Drive",
    "actions": ""
  },
  {
    "id": 171,
    "firstname": "Roxanne",
    "last_name": "Whicher",
    "email": "rwhicher4q@apple.com",
    "address": "2 Fairview Plaza",
    "actions": ""
  },
  {
    "id": 172,
    "firstname": "Nap",
    "last_name": "Whitlow",
    "email": "nwhitlow4r@freewebs.com",
    "address": "6 Manley Road",
    "actions": ""
  },
  {
    "id": 173,
    "firstname": "Moishe",
    "last_name": "Lourenco",
    "email": "mlourenco4s@storify.com",
    "address": "7892 Basil Alley",
    "actions": ""
  },
  {
    "id": 174,
    "firstname": "Derby",
    "last_name": "Dome",
    "email": "ddome4t@amazon.com",
    "address": "2 Portage Drive",
    "actions": ""
  },
  {
    "id": 175,
    "firstname": "Ddene",
    "last_name": "Partner",
    "email": "dpartner4u@opensource.org",
    "address": "0 Eastwood Way",
    "actions": ""
  },
  {
    "id": 176,
    "firstname": "Amery",
    "last_name": "Episcopio",
    "email": "aepiscopio4v@hubpages.com",
    "address": "44014 Kingsford Point",
    "actions": ""
  },
  {
    "id": 177,
    "firstname": "Waverley",
    "last_name": "Iaduccelli",
    "email": "wiaduccelli4w@51.la",
    "address": "9207 Monument Avenue",
    "actions": ""
  },
  {
    "id": 178,
    "firstname": "Nye",
    "last_name": "von Nassau",
    "email": "nvonnassau4x@dell.com",
    "address": "76020 Moulton Street",
    "actions": ""
  },
  {
    "id": 179,
    "firstname": "Logan",
    "last_name": "Sopper",
    "email": "lsopper4y@ucsd.edu",
    "address": "3 Sommers Street",
    "actions": ""
  },
  {
    "id": 180,
    "firstname": "Melloney",
    "last_name": "Martschik",
    "email": "mmartschik4z@chronoengine.com",
    "address": "061 Brickson Park Plaza",
    "actions": ""
  },
  {
    "id": 181,
    "firstname": "Friederike",
    "last_name": "Drescher",
    "email": "fdrescher50@army.mil",
    "address": "9 Evergreen Way",
    "actions": ""
  },
  {
    "id": 182,
    "firstname": "Cobby",
    "last_name": "Dovydenas",
    "email": "cdovydenas51@prweb.com",
    "address": "8853 Saint Paul Pass",
    "actions": ""
  },
  {
    "id": 183,
    "firstname": "Carmelita",
    "last_name": "Gloy",
    "email": "cgloy52@thetimes.co.uk",
    "address": "0740 Pawling Plaza",
    "actions": ""
  },
  {
    "id": 184,
    "firstname": "Veronica",
    "last_name": "Hintze",
    "email": "vhintze53@printfriendly.com",
    "address": "7 2nd Circle",
    "actions": ""
  },
  {
    "id": 185,
    "firstname": "Helli",
    "last_name": "Turnock",
    "email": "hturnock54@xing.com",
    "address": "631 6th Junction",
    "actions": ""
  },
  {
    "id": 186,
    "firstname": "Anny",
    "last_name": "Sapsforde",
    "email": "asapsforde55@chicagotribune.com",
    "address": "4681 Pearson Parkway",
    "actions": ""
  },
  {
    "id": 187,
    "firstname": "Ado",
    "last_name": "Almey",
    "email": "aalmey56@mediafire.com",
    "address": "24341 Ohio Parkway",
    "actions": ""
  },
  {
    "id": 188,
    "firstname": "Errol",
    "last_name": "Millichap",
    "email": "emillichap57@quantcast.com",
    "address": "9 Meadow Vale Junction",
    "actions": ""
  },
  {
    "id": 189,
    "firstname": "Selene",
    "last_name": "Smiz",
    "email": "ssmiz58@posterous.com",
    "address": "75074 Morning Street",
    "actions": ""
  },
  {
    "id": 190,
    "firstname": "Mariam",
    "last_name": "Fourcade",
    "email": "mfourcade59@bing.com",
    "address": "4918 Steensland Pass",
    "actions": ""
  },
  {
    "id": 191,
    "firstname": "Cati",
    "last_name": "Heigold",
    "email": "cheigold5a@google.co.jp",
    "address": "8 Delaware Hill",
    "actions": ""
  },
  {
    "id": 192,
    "firstname": "Lexis",
    "last_name": "McGarva",
    "email": "lmcgarva5b@redcross.org",
    "address": "7681 Fremont Place",
    "actions": ""
  },
  {
    "id": 193,
    "firstname": "Joline",
    "last_name": "Rudman",
    "email": "jrudman5c@hibu.com",
    "address": "335 Glendale Avenue",
    "actions": ""
  },
  {
    "id": 194,
    "firstname": "Jorey",
    "last_name": "Iaduccelli",
    "email": "jiaduccelli5d@illinois.edu",
    "address": "272 Crest Line Center",
    "actions": ""
  },
  {
    "id": 195,
    "firstname": "Hayward",
    "last_name": "Claw",
    "email": "hclaw5e@last.fm",
    "address": "2286 Redwing Place",
    "actions": ""
  },
  {
    "id": 196,
    "firstname": "Dana",
    "last_name": "Picknett",
    "email": "dpicknett5f@homestead.com",
    "address": "39 Acker Point",
    "actions": ""
  },
  {
    "id": 197,
    "firstname": "Joseito",
    "last_name": "MacPaike",
    "email": "jmacpaike5g@nps.gov",
    "address": "29687 Arrowood Circle",
    "actions": ""
  },
  {
    "id": 198,
    "firstname": "Stephana",
    "last_name": "Costanza",
    "email": "scostanza5h@nydailynews.com",
    "address": "3 Saint Paul Place",
    "actions": ""
  },
  {
    "id": 199,
    "firstname": "Garth",
    "last_name": "Freeth",
    "email": "gfreeth5i@java.com",
    "address": "6 Corscot Drive",
    "actions": ""
  },
  {
    "id": 200,
    "firstname": "Addie",
    "last_name": "Ginni",
    "email": "aginni5j@soup.io",
    "address": "2 Maywood Hill",
    "actions": ""
  },
  {
    "id": 201,
    "firstname": "Loise",
    "last_name": "Girardeau",
    "email": "lgirardeau5k@loc.gov",
    "address": "5130 Anthes Lane",
    "actions": ""
  },
  {
    "id": 202,
    "firstname": "Kailey",
    "last_name": "Scannell",
    "email": "kscannell5l@redcross.org",
    "address": "11 Delladonna Terrace",
    "actions": ""
  },
  {
    "id": 203,
    "firstname": "Arabelle",
    "last_name": "Brockhurst",
    "email": "abrockhurst5m@nymag.com",
    "address": "70 High Crossing Court",
    "actions": ""
  },
  {
    "id": 204,
    "firstname": "Holli",
    "last_name": "Couronne",
    "email": "hcouronne5n@histats.com",
    "address": "7683 Twin Pines Court",
    "actions": ""
  },
  {
    "id": 205,
    "firstname": "Vernor",
    "last_name": "Domini",
    "email": "vdomini5o@statcounter.com",
    "address": "46 Melody Parkway",
    "actions": ""
  },
  {
    "id": 206,
    "firstname": "Blanche",
    "last_name": "Berrow",
    "email": "bberrow5p@simplemachines.org",
    "address": "3 Kensington Circle",
    "actions": ""
  },
  {
    "id": 207,
    "firstname": "Wait",
    "last_name": "Bickle",
    "email": "wbickle5q@cloudflare.com",
    "address": "00 Lakeland Point",
    "actions": ""
  },
  {
    "id": 208,
    "firstname": "Cordula",
    "last_name": "Mandell",
    "email": "cmandell5r@reddit.com",
    "address": "8 Mcguire Lane",
    "actions": ""
  },
  {
    "id": 209,
    "firstname": "Serene",
    "last_name": "Duffit",
    "email": "sduffit5s@marriott.com",
    "address": "17164 Kim Terrace",
    "actions": ""
  },
  {
    "id": 210,
    "firstname": "Waite",
    "last_name": "Nutting",
    "email": "wnutting5t@hostgator.com",
    "address": "69221 Fairview Crossing",
    "actions": ""
  },
  {
    "id": 211,
    "firstname": "Bronny",
    "last_name": "Absolom",
    "email": "babsolom5u@spotify.com",
    "address": "3 Randy Lane",
    "actions": ""
  },
  {
    "id": 212,
    "firstname": "Sibbie",
    "last_name": "Fader",
    "email": "sfader5v@amazon.co.jp",
    "address": "79439 Novick Alley",
    "actions": ""
  },
  {
    "id": 213,
    "firstname": "Hugibert",
    "last_name": "Traher",
    "email": "htraher5w@whitehouse.gov",
    "address": "1999 South Pass",
    "actions": ""
  },
  {
    "id": 214,
    "firstname": "Olivie",
    "last_name": "Paris",
    "email": "oparis5x@dion.ne.jp",
    "address": "95261 Fremont Crossing",
    "actions": ""
  },
  {
    "id": 215,
    "firstname": "Joice",
    "last_name": "Flannigan",
    "email": "jflannigan5y@issuu.com",
    "address": "755 Reindahl Road",
    "actions": ""
  },
  {
    "id": 216,
    "firstname": "Freida",
    "last_name": "Keneforde",
    "email": "fkeneforde5z@cam.ac.uk",
    "address": "82 Tomscot Court",
    "actions": ""
  },
  {
    "id": 217,
    "firstname": "Royce",
    "last_name": "Willder",
    "email": "rwillder60@house.gov",
    "address": "721 Roth Plaza",
    "actions": ""
  },
  {
    "id": 218,
    "firstname": "Zenia",
    "last_name": "Loder",
    "email": "zloder61@weebly.com",
    "address": "21781 Hansons Drive",
    "actions": ""
  },
  {
    "id": 219,
    "firstname": "Randie",
    "last_name": "Lettice",
    "email": "rlettice62@behance.net",
    "address": "294 Badeau Place",
    "actions": ""
  },
  {
    "id": 220,
    "firstname": "Evey",
    "last_name": "Tuma",
    "email": "etuma63@moonfruit.com",
    "address": "3854 Ludington Parkway",
    "actions": ""
  },
  {
    "id": 221,
    "firstname": "Udall",
    "last_name": "Baker",
    "email": "ubaker64@harvard.edu",
    "address": "0 Forest Run Circle",
    "actions": ""
  },
  {
    "id": 222,
    "firstname": "Tilda",
    "last_name": "Adamini",
    "email": "tadamini65@reddit.com",
    "address": "49506 8th Drive",
    "actions": ""
  },
  {
    "id": 223,
    "firstname": "Julie",
    "last_name": "Bacon",
    "email": "jbacon66@blogspot.com",
    "address": "7 Graedel Drive",
    "actions": ""
  },
  {
    "id": 224,
    "firstname": "Ralph",
    "last_name": "Morson",
    "email": "rmorson67@liveinternet.ru",
    "address": "27669 Oxford Junction",
    "actions": ""
  },
  {
    "id": 225,
    "firstname": "Lucas",
    "last_name": "Futty",
    "email": "lfutty68@miitbeian.gov.cn",
    "address": "79444 Sullivan Alley",
    "actions": ""
  },
  {
    "id": 226,
    "firstname": "Tabitha",
    "last_name": "Orman",
    "email": "torman69@fotki.com",
    "address": "23 Westridge Alley",
    "actions": ""
  },
  {
    "id": 227,
    "firstname": "Correy",
    "last_name": "Izsak",
    "email": "cizsak6a@archive.org",
    "address": "00 Pleasure Place",
    "actions": ""
  },
  {
    "id": 228,
    "firstname": "Linnell",
    "last_name": "Kettleson",
    "email": "lkettleson6b@alibaba.com",
    "address": "753 Quincy Alley",
    "actions": ""
  },
  {
    "id": 229,
    "firstname": "Gusty",
    "last_name": "Lambarth",
    "email": "glambarth6c@wufoo.com",
    "address": "383 Derek Drive",
    "actions": ""
  },
  {
    "id": 230,
    "firstname": "Melvin",
    "last_name": "Gorgen",
    "email": "mgorgen6d@qq.com",
    "address": "75218 Clove Drive",
    "actions": ""
  },
  {
    "id": 231,
    "firstname": "Sheilah",
    "last_name": "Boulton",
    "email": "sboulton6e@ft.com",
    "address": "844 Manley Park",
    "actions": ""
  },
  {
    "id": 232,
    "firstname": "Vicki",
    "last_name": "Cogdell",
    "email": "vcogdell6f@china.com.cn",
    "address": "2016 Linden Hill",
    "actions": ""
  },
  {
    "id": 233,
    "firstname": "Francesco",
    "last_name": "Slowley",
    "email": "fslowley6g@wikimedia.org",
    "address": "23648 Arapahoe Hill",
    "actions": ""
  },
  {
    "id": 234,
    "firstname": "Frieda",
    "last_name": "Breinl",
    "email": "fbreinl6h@last.fm",
    "address": "551 Eastlawn Hill",
    "actions": ""
  },
  {
    "id": 235,
    "firstname": "Arther",
    "last_name": "Goullee",
    "email": "agoullee6i@typepad.com",
    "address": "8 Londonderry Circle",
    "actions": ""
  },
  {
    "id": 236,
    "firstname": "Harbert",
    "last_name": "Lortzing",
    "email": "hlortzing6j@4shared.com",
    "address": "5 Stuart Parkway",
    "actions": ""
  },
  {
    "id": 237,
    "firstname": "Sheelah",
    "last_name": "Godbert",
    "email": "sgodbert6k@creativecommons.org",
    "address": "49501 Acker Court",
    "actions": ""
  },
  {
    "id": 238,
    "firstname": "Alice",
    "last_name": "Gauford",
    "email": "agauford6l@oracle.com",
    "address": "33 Buena Vista Circle",
    "actions": ""
  },
  {
    "id": 239,
    "firstname": "Reilly",
    "last_name": "Polle",
    "email": "rpolle6m@cnet.com",
    "address": "621 Emmet Circle",
    "actions": ""
  },
  {
    "id": 240,
    "firstname": "Rochette",
    "last_name": "Escoffier",
    "email": "rescoffier6n@fc2.com",
    "address": "4 High Crossing Crossing",
    "actions": ""
  },
  {
    "id": 241,
    "firstname": "Bernete",
    "last_name": "Pashbee",
    "email": "bpashbee6o@cpanel.net",
    "address": "3 Laurel Avenue",
    "actions": ""
  },
  {
    "id": 242,
    "firstname": "Derby",
    "last_name": "Dawltrey",
    "email": "ddawltrey6p@cbslocal.com",
    "address": "58 Colorado Junction",
    "actions": ""
  },
  {
    "id": 243,
    "firstname": "Allyn",
    "last_name": "Itzchaky",
    "email": "aitzchaky6q@sitemeter.com",
    "address": "90030 Dixon Plaza",
    "actions": ""
  },
  {
    "id": 244,
    "firstname": "Starlene",
    "last_name": "Castri",
    "email": "scastri6r@answers.com",
    "address": "24 Heath Pass",
    "actions": ""
  },
  {
    "id": 245,
    "firstname": "Lilyan",
    "last_name": "Bellefant",
    "email": "lbellefant6s@github.io",
    "address": "011 Blackbird Plaza",
    "actions": ""
  },
  {
    "id": 246,
    "firstname": "Karla",
    "last_name": "Erswell",
    "email": "kerswell6t@ocn.ne.jp",
    "address": "0283 Crownhardt Trail",
    "actions": ""
  },
  {
    "id": 247,
    "firstname": "Cort",
    "last_name": "Smitherham",
    "email": "csmitherham6u@addthis.com",
    "address": "0 Welch Drive",
    "actions": ""
  },
  {
    "id": 248,
    "firstname": "Parrnell",
    "last_name": "Paule",
    "email": "ppaule6v@princeton.edu",
    "address": "5864 Gina Crossing",
    "actions": ""
  },
  {
    "id": 249,
    "firstname": "Heindrick",
    "last_name": "Farlowe",
    "email": "hfarlowe6w@multiply.com",
    "address": "74 Stoughton Point",
    "actions": ""
  },
  {
    "id": 250,
    "firstname": "Elissa",
    "last_name": "Sollett",
    "email": "esollett6x@usnews.com",
    "address": "1 Claremont Trail",
    "actions": ""
  },
  {
    "id": 251,
    "firstname": "Babs",
    "last_name": "Prester",
    "email": "bprester6y@pen.io",
    "address": "63876 Petterle Lane",
    "actions": ""
  },
  {
    "id": 252,
    "firstname": "Jedediah",
    "last_name": "Hounsham",
    "email": "jhounsham6z@shop-pro.jp",
    "address": "40 Coolidge Avenue",
    "actions": ""
  },
  {
    "id": 253,
    "firstname": "Bond",
    "last_name": "Clarage",
    "email": "bclarage70@latimes.com",
    "address": "8844 Everett Drive",
    "actions": ""
  },
  {
    "id": 254,
    "firstname": "Matt",
    "last_name": "Betterton",
    "email": "mbetterton71@youtu.be",
    "address": "5084 Bunting Pass",
    "actions": ""
  },
  {
    "id": 255,
    "firstname": "Corbie",
    "last_name": "Colam",
    "email": "ccolam72@altervista.org",
    "address": "14440 Oakridge Point",
    "actions": ""
  },
  {
    "id": 256,
    "firstname": "Ruddy",
    "last_name": "O'Kynsillaghe",
    "email": "rokynsillaghe73@lulu.com",
    "address": "5 Towne Street",
    "actions": ""
  },
  {
    "id": 257,
    "firstname": "Dasie",
    "last_name": "Brydie",
    "email": "dbrydie74@simplemachines.org",
    "address": "1 Schlimgen Road",
    "actions": ""
  },
  {
    "id": 258,
    "firstname": "Helenka",
    "last_name": "Rawcliff",
    "email": "hrawcliff75@msn.com",
    "address": "10 Burrows Avenue",
    "actions": ""
  },
  {
    "id": 259,
    "firstname": "Alleyn",
    "last_name": "Ogle",
    "email": "aogle76@mozilla.org",
    "address": "2970 Barnett Crossing",
    "actions": ""
  },
  {
    "id": 260,
    "firstname": "Lynne",
    "last_name": "Lindstrom",
    "email": "llindstrom77@fotki.com",
    "address": "0 Reindahl Hill",
    "actions": ""
  },
  {
    "id": 261,
    "firstname": "Celina",
    "last_name": "Ropars",
    "email": "cropars78@google.pl",
    "address": "61835 Lighthouse Bay Way",
    "actions": ""
  },
  {
    "id": 262,
    "firstname": "Gran",
    "last_name": "McPaike",
    "email": "gmcpaike79@163.com",
    "address": "83 Charing Cross Pass",
    "actions": ""
  },
  {
    "id": 263,
    "firstname": "Daveta",
    "last_name": "Lowis",
    "email": "dlowis7a@businesswire.com",
    "address": "84968 Laurel Crossing",
    "actions": ""
  },
  {
    "id": 264,
    "firstname": "Ambrose",
    "last_name": "Haville",
    "email": "ahaville7b@loc.gov",
    "address": "39143 Evergreen Street",
    "actions": ""
  },
  {
    "id": 265,
    "firstname": "Ulrike",
    "last_name": "Scrancher",
    "email": "uscrancher7c@apache.org",
    "address": "331 Dixon Center",
    "actions": ""
  },
  {
    "id": 266,
    "firstname": "Berk",
    "last_name": "Fesby",
    "email": "bfesby7d@ocn.ne.jp",
    "address": "1 Milwaukee Hill",
    "actions": ""
  },
  {
    "id": 267,
    "firstname": "Thorvald",
    "last_name": "Pay",
    "email": "tpay7e@geocities.jp",
    "address": "5556 Amoth Alley",
    "actions": ""
  },
  {
    "id": 268,
    "firstname": "Myrle",
    "last_name": "Larter",
    "email": "mlarter7f@networksolutions.com",
    "address": "19746 John Wall Center",
    "actions": ""
  },
  {
    "id": 269,
    "firstname": "Bernarr",
    "last_name": "Giggie",
    "email": "bgiggie7g@liveinternet.ru",
    "address": "8938 Loeprich Plaza",
    "actions": ""
  },
  {
    "id": 270,
    "firstname": "Jemimah",
    "last_name": "Godley",
    "email": "jgodley7h@upenn.edu",
    "address": "7 Ramsey Park",
    "actions": ""
  },
  {
    "id": 271,
    "firstname": "Tobias",
    "last_name": "Wesgate",
    "email": "twesgate7i@mac.com",
    "address": "2368 Valley Edge Hill",
    "actions": ""
  },
  {
    "id": 272,
    "firstname": "Arleen",
    "last_name": "Kinchlea",
    "email": "akinchlea7j@msu.edu",
    "address": "6076 Linden Center",
    "actions": ""
  },
  {
    "id": 273,
    "firstname": "Rosa",
    "last_name": "Peaseman",
    "email": "rpeaseman7k@samsung.com",
    "address": "0031 Hanson Trail",
    "actions": ""
  },
  {
    "id": 274,
    "firstname": "Misti",
    "last_name": "Zanitti",
    "email": "mzanitti7l@csmonitor.com",
    "address": "15773 Leroy Park",
    "actions": ""
  },
  {
    "id": 275,
    "firstname": "Halette",
    "last_name": "Buckleigh",
    "email": "hbuckleigh7m@ameblo.jp",
    "address": "1267 Londonderry Trail",
    "actions": ""
  },
  {
    "id": 276,
    "firstname": "Lennard",
    "last_name": "MacCarter",
    "email": "lmaccarter7n@nytimes.com",
    "address": "6 Mcguire Drive",
    "actions": ""
  },
  {
    "id": 277,
    "firstname": "Amberly",
    "last_name": "Dytham",
    "email": "adytham7o@spiegel.de",
    "address": "244 Farmco Hill",
    "actions": ""
  },
  {
    "id": 278,
    "firstname": "Alison",
    "last_name": "McPeeters",
    "email": "amcpeeters7p@amazon.co.jp",
    "address": "413 Independence Junction",
    "actions": ""
  },
  {
    "id": 279,
    "firstname": "Christen",
    "last_name": "Cardenas",
    "email": "ccardenas7q@unesco.org",
    "address": "69625 Merchant Trail",
    "actions": ""
  },
  {
    "id": 280,
    "firstname": "Jada",
    "last_name": "Pennini",
    "email": "jpennini7r@wp.com",
    "address": "5554 Thackeray Circle",
    "actions": ""
  },
  {
    "id": 281,
    "firstname": "Prentice",
    "last_name": "Whelband",
    "email": "pwhelband7s@tripadvisor.com",
    "address": "29187 Delladonna Street",
    "actions": ""
  },
  {
    "id": 282,
    "firstname": "Richy",
    "last_name": "Frisel",
    "email": "rfrisel7t@posterous.com",
    "address": "5345 Sullivan Trail",
    "actions": ""
  },
  {
    "id": 283,
    "firstname": "Worden",
    "last_name": "Edon",
    "email": "wedon7u@si.edu",
    "address": "242 Melody Parkway",
    "actions": ""
  },
  {
    "id": 284,
    "firstname": "Barbie",
    "last_name": "Velareal",
    "email": "bvelareal7v@dailymail.co.uk",
    "address": "7653 Havey Lane",
    "actions": ""
  },
  {
    "id": 285,
    "firstname": "Neron",
    "last_name": "Heinicke",
    "email": "nheinicke7w@about.me",
    "address": "32521 Briar Crest Hill",
    "actions": ""
  },
  {
    "id": 286,
    "firstname": "Billi",
    "last_name": "Skoggins",
    "email": "bskoggins7x@ycombinator.com",
    "address": "0837 Brickson Park Place",
    "actions": ""
  },
  {
    "id": 287,
    "firstname": "Velma",
    "last_name": "Irving",
    "email": "virving7y@wiley.com",
    "address": "8590 Cardinal Court",
    "actions": ""
  },
  {
    "id": 288,
    "firstname": "Solly",
    "last_name": "Cabrer",
    "email": "scabrer7z@ebay.co.uk",
    "address": "0 Waubesa Alley",
    "actions": ""
  },
  {
    "id": 289,
    "firstname": "Findlay",
    "last_name": "Kalkofer",
    "email": "fkalkofer80@nifty.com",
    "address": "30 Vidon Lane",
    "actions": ""
  },
  {
    "id": 290,
    "firstname": "Cynthie",
    "last_name": "Ottley",
    "email": "cottley81@abc.net.au",
    "address": "42 Jackson Place",
    "actions": ""
  },
  {
    "id": 291,
    "firstname": "Randell",
    "last_name": "Guerreau",
    "email": "rguerreau82@plala.or.jp",
    "address": "3330 3rd Road",
    "actions": ""
  },
  {
    "id": 292,
    "firstname": "Cristabel",
    "last_name": "Strewther",
    "email": "cstrewther83@pagesperso-orange.fr",
    "address": "0 Buena Vista Junction",
    "actions": ""
  },
  {
    "id": 293,
    "firstname": "Roxanne",
    "last_name": "Calwell",
    "email": "rcalwell84@google.com.hk",
    "address": "524 Eastwood Trail",
    "actions": ""
  },
  {
    "id": 294,
    "firstname": "Evy",
    "last_name": "Swayte",
    "email": "eswayte85@cyberchimps.com",
    "address": "3 Cardinal Center",
    "actions": ""
  },
  {
    "id": 295,
    "firstname": "Harman",
    "last_name": "Canfield",
    "email": "hcanfield86@about.com",
    "address": "479 Orin Junction",
    "actions": ""
  },
  {
    "id": 296,
    "firstname": "Frederigo",
    "last_name": "Houltham",
    "email": "fhoultham87@globo.com",
    "address": "658 Ohio Pass",
    "actions": ""
  },
  {
    "id": 297,
    "firstname": "Alice",
    "last_name": "Klug",
    "email": "aklug88@lulu.com",
    "address": "78 West Way",
    "actions": ""
  },
  {
    "id": 298,
    "firstname": "Ernesta",
    "last_name": "Twizell",
    "email": "etwizell89@delicious.com",
    "address": "87 Pankratz Crossing",
    "actions": ""
  },
  {
    "id": 299,
    "firstname": "Lea",
    "last_name": "Wakeman",
    "email": "lwakeman8a@time.com",
    "address": "4212 Prentice Parkway",
    "actions": ""
  },
  {
    "id": 300,
    "firstname": "Mel",
    "last_name": "Housam",
    "email": "mhousam8b@businessinsider.com",
    "address": "9784 Garrison Avenue",
    "actions": ""
  },
  {
    "id": 301,
    "firstname": "Tasia",
    "last_name": "Bottleson",
    "email": "tbottleson8c@chicagotribune.com",
    "address": "0909 Haas Place",
    "actions": ""
  },
  {
    "id": 302,
    "firstname": "Leigha",
    "last_name": "Choldcroft",
    "email": "lcholdcroft8d@dion.ne.jp",
    "address": "18 Mayer Junction",
    "actions": ""
  },
  {
    "id": 303,
    "firstname": "Darline",
    "last_name": "Leif",
    "email": "dleif8e@squarespace.com",
    "address": "54 Birchwood Street",
    "actions": ""
  },
  {
    "id": 304,
    "firstname": "Carolyne",
    "last_name": "Osgar",
    "email": "cosgar8f@archive.org",
    "address": "35884 Randy Junction",
    "actions": ""
  },
  {
    "id": 305,
    "firstname": "Euphemia",
    "last_name": "Joplin",
    "email": "ejoplin8g@blogs.com",
    "address": "6342 Surrey Way",
    "actions": ""
  },
  {
    "id": 306,
    "firstname": "Ellette",
    "last_name": "Noore",
    "email": "enoore8h@free.fr",
    "address": "27 Jenifer Point",
    "actions": ""
  },
  {
    "id": 307,
    "firstname": "Estell",
    "last_name": "Heino",
    "email": "eheino8i@joomla.org",
    "address": "8620 Northland Street",
    "actions": ""
  },
  {
    "id": 308,
    "firstname": "Pollyanna",
    "last_name": "Huonic",
    "email": "phuonic8j@pinterest.com",
    "address": "41 Hallows Junction",
    "actions": ""
  },
  {
    "id": 309,
    "firstname": "Harlie",
    "last_name": "Moran",
    "email": "hmoran8k@cdc.gov",
    "address": "9809 Carpenter Plaza",
    "actions": ""
  },
  {
    "id": 310,
    "firstname": "Merilee",
    "last_name": "Willers",
    "email": "mwillers8l@weibo.com",
    "address": "82 Porter Center",
    "actions": ""
  },
  {
    "id": 311,
    "firstname": "Ethelda",
    "last_name": "Jobb",
    "email": "ejobb8m@google.com",
    "address": "9774 Lake View Plaza",
    "actions": ""
  },
  {
    "id": 312,
    "firstname": "Justinn",
    "last_name": "Barkworth",
    "email": "jbarkworth8n@gnu.org",
    "address": "49 Forster Hill",
    "actions": ""
  },
  {
    "id": 313,
    "firstname": "Clotilda",
    "last_name": "Vanderson",
    "email": "cvanderson8o@shinystat.com",
    "address": "1613 Northview Drive",
    "actions": ""
  },
  {
    "id": 314,
    "firstname": "Maurine",
    "last_name": "Redferne",
    "email": "mredferne8p@noaa.gov",
    "address": "991 Twin Pines Alley",
    "actions": ""
  },
  {
    "id": 315,
    "firstname": "Rodolfo",
    "last_name": "Gowers",
    "email": "rgowers8q@smugmug.com",
    "address": "10 Havey Lane",
    "actions": ""
  },
  {
    "id": 316,
    "firstname": "Kipper",
    "last_name": "Overstall",
    "email": "koverstall8r@timesonline.co.uk",
    "address": "81 Spohn Terrace",
    "actions": ""
  },
  {
    "id": 317,
    "firstname": "Maisey",
    "last_name": "Liddicoat",
    "email": "mliddicoat8s@flickr.com",
    "address": "26366 Carberry Drive",
    "actions": ""
  },
  {
    "id": 318,
    "firstname": "Klarika",
    "last_name": "Waterhouse",
    "email": "kwaterhouse8t@alexa.com",
    "address": "4 Meadow Ridge Pass",
    "actions": ""
  },
  {
    "id": 319,
    "firstname": "Benoite",
    "last_name": "Vasser",
    "email": "bvasser8u@domainmarket.com",
    "address": "0 Norway Maple Trail",
    "actions": ""
  },
  {
    "id": 320,
    "firstname": "Walton",
    "last_name": "Elfes",
    "email": "welfes8v@surveymonkey.com",
    "address": "7254 Calypso Plaza",
    "actions": ""
  },
  {
    "id": 321,
    "firstname": "Coleman",
    "last_name": "Clemo",
    "email": "cclemo8w@gmpg.org",
    "address": "9632 Karstens Drive",
    "actions": ""
  },
  {
    "id": 322,
    "firstname": "Eyde",
    "last_name": "Hollibone",
    "email": "ehollibone8x@cbc.ca",
    "address": "132 Victoria Junction",
    "actions": ""
  },
  {
    "id": 323,
    "firstname": "Drusilla",
    "last_name": "Schiesterl",
    "email": "dschiesterl8y@vimeo.com",
    "address": "32 Oneill Way",
    "actions": ""
  },
  {
    "id": 324,
    "firstname": "Elset",
    "last_name": "Cuxson",
    "email": "ecuxson8z@phpbb.com",
    "address": "65546 Birchwood Court",
    "actions": ""
  },
  {
    "id": 325,
    "firstname": "Husain",
    "last_name": "Dowyer",
    "email": "hdowyer90@so-net.ne.jp",
    "address": "59591 Sunnyside Court",
    "actions": ""
  },
  {
    "id": 326,
    "firstname": "Frankie",
    "last_name": "Ghelardoni",
    "email": "fghelardoni91@redcross.org",
    "address": "432 Lakewood Gardens Place",
    "actions": ""
  },
  {
    "id": 327,
    "firstname": "Gilbertina",
    "last_name": "Warrior",
    "email": "gwarrior92@bbc.co.uk",
    "address": "63771 Dryden Place",
    "actions": ""
  },
  {
    "id": 328,
    "firstname": "Valina",
    "last_name": "Wilse",
    "email": "vwilse93@gnu.org",
    "address": "0715 Mariners Cove Junction",
    "actions": ""
  },
  {
    "id": 329,
    "firstname": "Derick",
    "last_name": "Rapa",
    "email": "drapa94@weebly.com",
    "address": "9 Basil Court",
    "actions": ""
  },
  {
    "id": 330,
    "firstname": "Parrnell",
    "last_name": "Burth",
    "email": "pburth95@studiopress.com",
    "address": "36 Ramsey Terrace",
    "actions": ""
  },
  {
    "id": 331,
    "firstname": "Orton",
    "last_name": "Stockow",
    "email": "ostockow96@cdc.gov",
    "address": "88 Alpine Junction",
    "actions": ""
  },
  {
    "id": 332,
    "firstname": "Wilbur",
    "last_name": "MacAirt",
    "email": "wmacairt97@about.com",
    "address": "2848 Bunting Terrace",
    "actions": ""
  },
  {
    "id": 333,
    "firstname": "Patton",
    "last_name": "Shoebotham",
    "email": "pshoebotham98@cornell.edu",
    "address": "9 Ridge Oak Junction",
    "actions": ""
  },
  {
    "id": 334,
    "firstname": "Nadia",
    "last_name": "Kurdani",
    "email": "nkurdani99@barnesandnoble.com",
    "address": "7 Brentwood Center",
    "actions": ""
  },
  {
    "id": 335,
    "firstname": "Rayner",
    "last_name": "Dibdale",
    "email": "rdibdale9a@i2i.jp",
    "address": "25 Service Circle",
    "actions": ""
  },
  {
    "id": 336,
    "firstname": "Sabra",
    "last_name": "Fazzioli",
    "email": "sfazzioli9b@123-reg.co.uk",
    "address": "94076 Jenifer Terrace",
    "actions": ""
  },
  {
    "id": 337,
    "firstname": "Emmy",
    "last_name": "Sharrier",
    "email": "esharrier9c@pinterest.com",
    "address": "89033 Vernon Center",
    "actions": ""
  },
  {
    "id": 338,
    "firstname": "Fredericka",
    "last_name": "Rubica",
    "email": "frubica9d@statcounter.com",
    "address": "84688 Tennyson Place",
    "actions": ""
  },
  {
    "id": 339,
    "firstname": "Abe",
    "last_name": "Weddell",
    "email": "aweddell9e@phoca.cz",
    "address": "39019 Vidon Court",
    "actions": ""
  },
  {
    "id": 340,
    "firstname": "Nari",
    "last_name": "Le Strange",
    "email": "nlestrange9f@liveinternet.ru",
    "address": "7177 Lindbergh Circle",
    "actions": ""
  },
  {
    "id": 341,
    "firstname": "Rriocard",
    "last_name": "Meechan",
    "email": "rmeechan9g@hc360.com",
    "address": "71 Twin Pines Way",
    "actions": ""
  },
  {
    "id": 342,
    "firstname": "Arlen",
    "last_name": "Clarke",
    "email": "aclarke9h@xinhuanet.com",
    "address": "02 Luster Circle",
    "actions": ""
  },
  {
    "id": 343,
    "firstname": "Avie",
    "last_name": "Chiplen",
    "email": "achiplen9i@va.gov",
    "address": "40 Schmedeman Point",
    "actions": ""
  },
  {
    "id": 344,
    "firstname": "Gasper",
    "last_name": "Moy",
    "email": "gmoy9j@drupal.org",
    "address": "2 Hintze Alley",
    "actions": ""
  },
  {
    "id": 345,
    "firstname": "Ynes",
    "last_name": "Craig",
    "email": "ycraig9k@lycos.com",
    "address": "21576 David Street",
    "actions": ""
  },
  {
    "id": 346,
    "firstname": "Sella",
    "last_name": "Swale",
    "email": "sswale9l@youtube.com",
    "address": "05 Center Alley",
    "actions": ""
  },
  {
    "id": 347,
    "firstname": "Jaclyn",
    "last_name": "Fryett",
    "email": "jfryett9m@amazon.co.jp",
    "address": "95 Miller Parkway",
    "actions": ""
  },
  {
    "id": 348,
    "firstname": "Noel",
    "last_name": "Lutas",
    "email": "nlutas9n@chicagotribune.com",
    "address": "339 Johnson Lane",
    "actions": ""
  },
  {
    "id": 349,
    "firstname": "Louisette",
    "last_name": "Jacobowicz",
    "email": "ljacobowicz9o@webmd.com",
    "address": "87 Talisman Avenue",
    "actions": ""
  },
  {
    "id": 350,
    "firstname": "Andrea",
    "last_name": "Tower",
    "email": "atower9p@irs.gov",
    "address": "4617 Mcbride Trail",
    "actions": ""
  },
  {
    "id": 351,
    "firstname": "Jacinta",
    "last_name": "Liffey",
    "email": "jliffey9q@paypal.com",
    "address": "72 Ridgeway Alley",
    "actions": ""
  },
  {
    "id": 352,
    "firstname": "Wells",
    "last_name": "Besant",
    "email": "wbesant9r@answers.com",
    "address": "2 Randy Alley",
    "actions": ""
  },
  {
    "id": 353,
    "firstname": "Son",
    "last_name": "Franciotti",
    "email": "sfranciotti9s@omniture.com",
    "address": "17 Mariners Cove Trail",
    "actions": ""
  },
  {
    "id": 354,
    "firstname": "Phillip",
    "last_name": "O'Lehane",
    "email": "polehane9t@blogger.com",
    "address": "8 Red Cloud Avenue",
    "actions": ""
  },
  {
    "id": 355,
    "firstname": "Alecia",
    "last_name": "Ciobotaru",
    "email": "aciobotaru9u@eventbrite.com",
    "address": "2 Ramsey Terrace",
    "actions": ""
  },
  {
    "id": 356,
    "firstname": "Salmon",
    "last_name": "Greaser",
    "email": "sgreaser9v@archive.org",
    "address": "8861 Utah Place",
    "actions": ""
  },
  {
    "id": 357,
    "firstname": "Maribelle",
    "last_name": "Jenney",
    "email": "mjenney9w@newyorker.com",
    "address": "71 Ruskin Circle",
    "actions": ""
  },
  {
    "id": 358,
    "firstname": "Licha",
    "last_name": "Minchinton",
    "email": "lminchinton9x@mozilla.com",
    "address": "88562 Lighthouse Bay Avenue",
    "actions": ""
  },
  {
    "id": 359,
    "firstname": "Yorker",
    "last_name": "Terran",
    "email": "yterran9y@netscape.com",
    "address": "35037 Schurz Way",
    "actions": ""
  },
  {
    "id": 360,
    "firstname": "Bevin",
    "last_name": "Owenson",
    "email": "bowenson9z@friendfeed.com",
    "address": "58 Russell Hill",
    "actions": ""
  },
  {
    "id": 361,
    "firstname": "Junette",
    "last_name": "Storey",
    "email": "jstoreya0@businessweek.com",
    "address": "72656 Havey Alley",
    "actions": ""
  },
  {
    "id": 362,
    "firstname": "Tallie",
    "last_name": "Mulmuray",
    "email": "tmulmuraya1@jimdo.com",
    "address": "783 Anniversary Street",
    "actions": ""
  },
  {
    "id": 363,
    "firstname": "Darby",
    "last_name": "Arnaudot",
    "email": "darnaudota2@upenn.edu",
    "address": "79755 Manley Point",
    "actions": ""
  },
  {
    "id": 364,
    "firstname": "Constantin",
    "last_name": "Ivantyev",
    "email": "civantyeva3@google.ru",
    "address": "48 Jana Crossing",
    "actions": ""
  },
  {
    "id": 365,
    "firstname": "Kimmi",
    "last_name": "Cousans",
    "email": "kcousansa4@washingtonpost.com",
    "address": "00 Miller Hill",
    "actions": ""
  },
  {
    "id": 366,
    "firstname": "Jerrold",
    "last_name": "Hobben",
    "email": "jhobbena5@csmonitor.com",
    "address": "16 Stoughton Trail",
    "actions": ""
  },
  {
    "id": 367,
    "firstname": "Sunny",
    "last_name": "Cator",
    "email": "scatora6@friendfeed.com",
    "address": "40 Declaration Drive",
    "actions": ""
  },
  {
    "id": 368,
    "firstname": "Cinnamon",
    "last_name": "Choffin",
    "email": "cchoffina7@free.fr",
    "address": "29 Union Way",
    "actions": ""
  },
  {
    "id": 369,
    "firstname": "Eugenie",
    "last_name": "Shoard",
    "email": "eshoarda8@upenn.edu",
    "address": "1428 Brickson Park Street",
    "actions": ""
  },
  {
    "id": 370,
    "firstname": "Dorie",
    "last_name": "Dowdam",
    "email": "ddowdama9@indiatimes.com",
    "address": "7606 Shoshone Avenue",
    "actions": ""
  },
  {
    "id": 371,
    "firstname": "Catharina",
    "last_name": "Woodyatt",
    "email": "cwoodyattaa@statcounter.com",
    "address": "691 Garrison Avenue",
    "actions": ""
  },
  {
    "id": 372,
    "firstname": "Daphene",
    "last_name": "Earsman",
    "email": "dearsmanab@yahoo.co.jp",
    "address": "7 Straubel Pass",
    "actions": ""
  },
  {
    "id": 373,
    "firstname": "Byrom",
    "last_name": "Nutman",
    "email": "bnutmanac@google.com.au",
    "address": "2283 Thackeray Parkway",
    "actions": ""
  },
  {
    "id": 374,
    "firstname": "Ashien",
    "last_name": "Castan",
    "email": "acastanad@spiegel.de",
    "address": "4262 Tomscot Center",
    "actions": ""
  },
  {
    "id": 375,
    "firstname": "Lotta",
    "last_name": "Laker",
    "email": "llakerae@printfriendly.com",
    "address": "3557 Cascade Pass",
    "actions": ""
  },
  {
    "id": 376,
    "firstname": "Lurlene",
    "last_name": "Featherby",
    "email": "lfeatherbyaf@unc.edu",
    "address": "66921 Holy Cross Drive",
    "actions": ""
  },
  {
    "id": 377,
    "firstname": "Ronny",
    "last_name": "Janiak",
    "email": "rjaniakag@rambler.ru",
    "address": "03 Shelley Avenue",
    "actions": ""
  },
  {
    "id": 378,
    "firstname": "Nickie",
    "last_name": "Skidmore",
    "email": "nskidmoreah@delicious.com",
    "address": "804 Lyons Center",
    "actions": ""
  },
  {
    "id": 379,
    "firstname": "Ailis",
    "last_name": "Servant",
    "email": "aservantai@dot.gov",
    "address": "8130 Evergreen Crossing",
    "actions": ""
  },
  {
    "id": 380,
    "firstname": "Bria",
    "last_name": "Catterell",
    "email": "bcatterellaj@phoca.cz",
    "address": "6 Vermont Plaza",
    "actions": ""
  },
  {
    "id": 381,
    "firstname": "Torin",
    "last_name": "McGhee",
    "email": "tmcgheeak@alibaba.com",
    "address": "73152 Merry Street",
    "actions": ""
  },
  {
    "id": 382,
    "firstname": "Trever",
    "last_name": "Flucker",
    "email": "tfluckeral@icq.com",
    "address": "490 Del Mar Street",
    "actions": ""
  },
  {
    "id": 383,
    "firstname": "Fabio",
    "last_name": "Prop",
    "email": "fpropam@admin.ch",
    "address": "11356 Anniversary Drive",
    "actions": ""
  },
  {
    "id": 384,
    "firstname": "Sidonnie",
    "last_name": "Trahearn",
    "email": "strahearnan@oracle.com",
    "address": "170 Delaware Pass",
    "actions": ""
  },
  {
    "id": 385,
    "firstname": "Ailyn",
    "last_name": "Emblen",
    "email": "aemblenao@reuters.com",
    "address": "3503 Mallory Trail",
    "actions": ""
  },
  {
    "id": 386,
    "firstname": "Angelle",
    "last_name": "Leel",
    "email": "aleelap@yahoo.com",
    "address": "8422 Scoville Lane",
    "actions": ""
  },
  {
    "id": 387,
    "firstname": "Sib",
    "last_name": "Arthurs",
    "email": "sarthursaq@cisco.com",
    "address": "1 Ronald Regan Road",
    "actions": ""
  },
  {
    "id": 388,
    "firstname": "Ellissa",
    "last_name": "Bygrove",
    "email": "ebygrovear@edublogs.org",
    "address": "29353 Mifflin Way",
    "actions": ""
  },
  {
    "id": 389,
    "firstname": "Letti",
    "last_name": "Croshaw",
    "email": "lcroshawas@1688.com",
    "address": "853 Springs Street",
    "actions": ""
  },
  {
    "id": 390,
    "firstname": "Nerta",
    "last_name": "Buckoke",
    "email": "nbuckokeat@patch.com",
    "address": "0 Kensington Park",
    "actions": ""
  },
  {
    "id": 391,
    "firstname": "Mort",
    "last_name": "Retallick",
    "email": "mretallickau@goo.gl",
    "address": "140 Carey Hill",
    "actions": ""
  },
  {
    "id": 392,
    "firstname": "Desirae",
    "last_name": "Kindleysides",
    "email": "dkindleysidesav@uiuc.edu",
    "address": "5268 Morrow Junction",
    "actions": ""
  },
  {
    "id": 393,
    "firstname": "Verla",
    "last_name": "Good",
    "email": "vgoodaw@google.co.uk",
    "address": "434 Schurz Street",
    "actions": ""
  },
  {
    "id": 394,
    "firstname": "Morrie",
    "last_name": "Faraker",
    "email": "mfarakerax@google.nl",
    "address": "90670 Lindbergh Hill",
    "actions": ""
  },
  {
    "id": 395,
    "firstname": "Bobbe",
    "last_name": "Benbow",
    "email": "bbenboway@army.mil",
    "address": "021 Burning Wood Way",
    "actions": ""
  },
  {
    "id": 396,
    "firstname": "Janaya",
    "last_name": "Rubega",
    "email": "jrubegaaz@ameblo.jp",
    "address": "59150 Cardinal Point",
    "actions": ""
  },
  {
    "id": 397,
    "firstname": "Burl",
    "last_name": "Thomtson",
    "email": "bthomtsonb0@mediafire.com",
    "address": "34891 Jana Drive",
    "actions": ""
  },
  {
    "id": 398,
    "firstname": "Doreen",
    "last_name": "Kohrs",
    "email": "dkohrsb1@e-recht24.de",
    "address": "59872 Pierstorff Avenue",
    "actions": ""
  },
  {
    "id": 399,
    "firstname": "Chantalle",
    "last_name": "Goodban",
    "email": "cgoodbanb2@icio.us",
    "address": "814 Melrose Crossing",
    "actions": ""
  },
  {
    "id": 400,
    "firstname": "Julia",
    "last_name": "Commings",
    "email": "jcommingsb3@cdbaby.com",
    "address": "1 3rd Trail",
    "actions": ""
  },
  {
    "id": 401,
    "firstname": "Toinette",
    "last_name": "Gozney",
    "email": "tgozneyb4@cbsnews.com",
    "address": "9534 Jay Hill",
    "actions": ""
  },
  {
    "id": 402,
    "firstname": "Bekki",
    "last_name": "McBrearty",
    "email": "bmcbreartyb5@ebay.com",
    "address": "7024 Heath Lane",
    "actions": ""
  },
  {
    "id": 403,
    "firstname": "Frankie",
    "last_name": "Iacovini",
    "email": "fiacovinib6@usa.gov",
    "address": "4290 Melody Crossing",
    "actions": ""
  },
  {
    "id": 404,
    "firstname": "Alaine",
    "last_name": "Mougeot",
    "email": "amougeotb7@ustream.tv",
    "address": "67 Judy Court",
    "actions": ""
  },
  {
    "id": 405,
    "firstname": "Fern",
    "last_name": "Ysson",
    "email": "fyssonb8@answers.com",
    "address": "97633 Dennis Place",
    "actions": ""
  },
  {
    "id": 406,
    "firstname": "Stefano",
    "last_name": "Aloshikin",
    "email": "saloshikinb9@mlb.com",
    "address": "4945 Dakota Terrace",
    "actions": ""
  },
  {
    "id": 407,
    "firstname": "Corney",
    "last_name": "Imlach",
    "email": "cimlachba@utexas.edu",
    "address": "79728 Dryden Junction",
    "actions": ""
  },
  {
    "id": 408,
    "firstname": "Brigit",
    "last_name": "Yardley",
    "email": "byardleybb@tiny.cc",
    "address": "6 Rusk Parkway",
    "actions": ""
  },
  {
    "id": 409,
    "firstname": "Kata",
    "last_name": "Iacopo",
    "email": "kiacopobc@wikia.com",
    "address": "824 Lukken Alley",
    "actions": ""
  },
  {
    "id": 410,
    "firstname": "Benedicto",
    "last_name": "Kennady",
    "email": "bkennadybd@npr.org",
    "address": "7495 Manitowish Point",
    "actions": ""
  },
  {
    "id": 411,
    "firstname": "Emiline",
    "last_name": "Wraxall",
    "email": "ewraxallbe@ycombinator.com",
    "address": "30973 Novick Point",
    "actions": ""
  },
  {
    "id": 412,
    "firstname": "Dulcea",
    "last_name": "Cabera",
    "email": "dcaberabf@sbwire.com",
    "address": "5 Browning Parkway",
    "actions": ""
  },
  {
    "id": 413,
    "firstname": "Mathian",
    "last_name": "St. Ledger",
    "email": "mstledgerbg@lulu.com",
    "address": "45 Doe Crossing Trail",
    "actions": ""
  },
  {
    "id": 414,
    "firstname": "Stefania",
    "last_name": "Elham",
    "email": "selhambh@apple.com",
    "address": "75 Buell Point",
    "actions": ""
  },
  {
    "id": 415,
    "firstname": "Jocelyne",
    "last_name": "Lorkins",
    "email": "jlorkinsbi@wunderground.com",
    "address": "7 Menomonie Alley",
    "actions": ""
  },
  {
    "id": 416,
    "firstname": "Shellysheldon",
    "last_name": "Withey",
    "email": "switheybj@wisc.edu",
    "address": "97116 Ruskin Alley",
    "actions": ""
  },
  {
    "id": 417,
    "firstname": "Cissiee",
    "last_name": "Goodier",
    "email": "cgoodierbk@omniture.com",
    "address": "87 Paget Junction",
    "actions": ""
  },
  {
    "id": 418,
    "firstname": "Maxy",
    "last_name": "Lumsdaine",
    "email": "mlumsdainebl@zdnet.com",
    "address": "029 Fallview Circle",
    "actions": ""
  },
  {
    "id": 419,
    "firstname": "Fergus",
    "last_name": "Huffy",
    "email": "fhuffybm@people.com.cn",
    "address": "8 Anthes Way",
    "actions": ""
  },
  {
    "id": 420,
    "firstname": "Egon",
    "last_name": "Drohane",
    "email": "edrohanebn@squarespace.com",
    "address": "237 Golf View Trail",
    "actions": ""
  },
  {
    "id": 421,
    "firstname": "Felipe",
    "last_name": "Delong",
    "email": "fdelongbo@forbes.com",
    "address": "4768 Mendota Avenue",
    "actions": ""
  },
  {
    "id": 422,
    "firstname": "Hobard",
    "last_name": "Ghest",
    "email": "hghestbp@techcrunch.com",
    "address": "53 East Terrace",
    "actions": ""
  },
  {
    "id": 423,
    "firstname": "Lisbeth",
    "last_name": "Camelia",
    "email": "lcameliabq@alibaba.com",
    "address": "35 Oakridge Crossing",
    "actions": ""
  },
  {
    "id": 424,
    "firstname": "Zandra",
    "last_name": "Terzza",
    "email": "zterzzabr@ed.gov",
    "address": "9 Debra Plaza",
    "actions": ""
  },
  {
    "id": 425,
    "firstname": "Etan",
    "last_name": "Lutman",
    "email": "elutmanbs@dropbox.com",
    "address": "5044 Eliot Street",
    "actions": ""
  },
  {
    "id": 426,
    "firstname": "Katine",
    "last_name": "Tremayne",
    "email": "ktremaynebt@yahoo.com",
    "address": "220 Sunnyside Alley",
    "actions": ""
  },
  {
    "id": 427,
    "firstname": "Gilligan",
    "last_name": "Riden",
    "email": "gridenbu@deviantart.com",
    "address": "8999 Hanson Terrace",
    "actions": ""
  },
  {
    "id": 428,
    "firstname": "Matti",
    "last_name": "Pottage",
    "email": "mpottagebv@histats.com",
    "address": "4055 Village Green Trail",
    "actions": ""
  },
  {
    "id": 429,
    "firstname": "Elvyn",
    "last_name": "Hovert",
    "email": "ehovertbw@360.cn",
    "address": "182 Mayfield Park",
    "actions": ""
  },
  {
    "id": 430,
    "firstname": "Sid",
    "last_name": "Castilla",
    "email": "scastillabx@nps.gov",
    "address": "65 Oriole Crossing",
    "actions": ""
  },
  {
    "id": 431,
    "firstname": "Guillemette",
    "last_name": "Woollin",
    "email": "gwoollinby@sbwire.com",
    "address": "66022 Merrick Parkway",
    "actions": ""
  },
  {
    "id": 432,
    "firstname": "Sharona",
    "last_name": "Burrill",
    "email": "sburrillbz@baidu.com",
    "address": "50 Hauk Avenue",
    "actions": ""
  },
  {
    "id": 433,
    "firstname": "Chrissie",
    "last_name": "Moxon",
    "email": "cmoxonc0@alibaba.com",
    "address": "968 Sachs Hill",
    "actions": ""
  },
  {
    "id": 434,
    "firstname": "Anatole",
    "last_name": "Stracey",
    "email": "astraceyc1@bloglines.com",
    "address": "2138 Cascade Alley",
    "actions": ""
  },
  {
    "id": 435,
    "firstname": "Lavena",
    "last_name": "Duberry",
    "email": "lduberryc2@cpanel.net",
    "address": "27 Scoville Avenue",
    "actions": ""
  },
  {
    "id": 436,
    "firstname": "Gizela",
    "last_name": "Edmondson",
    "email": "gedmondsonc3@about.me",
    "address": "99775 Golf Course Place",
    "actions": ""
  },
  {
    "id": 437,
    "firstname": "Casey",
    "last_name": "Matula",
    "email": "cmatulac4@skype.com",
    "address": "34535 Beilfuss Pass",
    "actions": ""
  },
  {
    "id": 438,
    "firstname": "Sara-ann",
    "last_name": "Battista",
    "email": "sbattistac5@vkontakte.ru",
    "address": "51522 Merrick Drive",
    "actions": ""
  },
  {
    "id": 439,
    "firstname": "Scarface",
    "last_name": "Abrahamowitcz",
    "email": "sabrahamowitczc6@barnesandnoble.com",
    "address": "882 Schlimgen Court",
    "actions": ""
  },
  {
    "id": 440,
    "firstname": "Leola",
    "last_name": "Witchalls",
    "email": "lwitchallsc7@ftc.gov",
    "address": "4 Buena Vista Road",
    "actions": ""
  },
  {
    "id": 441,
    "firstname": "Bram",
    "last_name": "Dwyr",
    "email": "bdwyrc8@tumblr.com",
    "address": "88 Forest Run Avenue",
    "actions": ""
  },
  {
    "id": 442,
    "firstname": "Haslett",
    "last_name": "Tingcomb",
    "email": "htingcombc9@netlog.com",
    "address": "319 Nancy Plaza",
    "actions": ""
  },
  {
    "id": 443,
    "firstname": "Vick",
    "last_name": "Randales",
    "email": "vrandalesca@google.com.br",
    "address": "45 Lunder Road",
    "actions": ""
  },
  {
    "id": 444,
    "firstname": "Amery",
    "last_name": "MacEvilly",
    "email": "amacevillycb@artisteer.com",
    "address": "2 Lake View Place",
    "actions": ""
  },
  {
    "id": 445,
    "firstname": "Salvatore",
    "last_name": "Feirn",
    "email": "sfeirncc@craigslist.org",
    "address": "918 Derek Point",
    "actions": ""
  },
  {
    "id": 446,
    "firstname": "Lockwood",
    "last_name": "Blondel",
    "email": "lblondelcd@home.pl",
    "address": "3554 Lakewood Crossing",
    "actions": ""
  },
  {
    "id": 447,
    "firstname": "Beaufort",
    "last_name": "Caught",
    "email": "bcaughtce@oracle.com",
    "address": "51794 Bobwhite Park",
    "actions": ""
  },
  {
    "id": 448,
    "firstname": "Rubia",
    "last_name": "Hawgood",
    "email": "rhawgoodcf@canalblog.com",
    "address": "7171 Eagan Junction",
    "actions": ""
  },
  {
    "id": 449,
    "firstname": "Avril",
    "last_name": "Spolton",
    "email": "aspoltoncg@army.mil",
    "address": "841 Ilene Crossing",
    "actions": ""
  },
  {
    "id": 450,
    "firstname": "Adolph",
    "last_name": "Eddisforth",
    "email": "aeddisforthch@csmonitor.com",
    "address": "173 Marcy Pass",
    "actions": ""
  },
  {
    "id": 451,
    "firstname": "Kikelia",
    "last_name": "Royds",
    "email": "kroydsci@nps.gov",
    "address": "0556 Sauthoff Lane",
    "actions": ""
  },
  {
    "id": 452,
    "firstname": "Pasquale",
    "last_name": "Keirle",
    "email": "pkeirlecj@meetup.com",
    "address": "8825 Bartelt Drive",
    "actions": ""
  },
  {
    "id": 453,
    "firstname": "Mufi",
    "last_name": "Serle",
    "email": "mserleck@devhub.com",
    "address": "550 Vahlen Center",
    "actions": ""
  },
  {
    "id": 454,
    "firstname": "Demott",
    "last_name": "Spindler",
    "email": "dspindlercl@liveinternet.ru",
    "address": "182 Victoria Place",
    "actions": ""
  },
  {
    "id": 455,
    "firstname": "Angil",
    "last_name": "Pinnock",
    "email": "apinnockcm@gizmodo.com",
    "address": "98 Del Sol Avenue",
    "actions": ""
  },
  {
    "id": 456,
    "firstname": "Daune",
    "last_name": "Prando",
    "email": "dprandocn@nifty.com",
    "address": "506 Springs Lane",
    "actions": ""
  },
  {
    "id": 457,
    "firstname": "Tobiah",
    "last_name": "Trevance",
    "email": "ttrevanceco@g.co",
    "address": "95 Center Lane",
    "actions": ""
  },
  {
    "id": 458,
    "firstname": "Jessee",
    "last_name": "Gates",
    "email": "jgatescp@pinterest.com",
    "address": "19828 Clove Parkway",
    "actions": ""
  },
  {
    "id": 459,
    "firstname": "Evangelina",
    "last_name": "Allcroft",
    "email": "eallcroftcq@nifty.com",
    "address": "70351 Moose Crossing",
    "actions": ""
  },
  {
    "id": 460,
    "firstname": "Boonie",
    "last_name": "Dewane",
    "email": "bdewanecr@ameblo.jp",
    "address": "689 Tennessee Plaza",
    "actions": ""
  },
  {
    "id": 461,
    "firstname": "Binnie",
    "last_name": "Kembrey",
    "email": "bkembreycs@mashable.com",
    "address": "78 Leroy Street",
    "actions": ""
  },
  {
    "id": 462,
    "firstname": "Gianni",
    "last_name": "Harlock",
    "email": "gharlockct@soup.io",
    "address": "73 Chive Circle",
    "actions": ""
  },
  {
    "id": 463,
    "firstname": "Ricky",
    "last_name": "Coleman",
    "email": "rcolemancu@t-online.de",
    "address": "2872 Jenna Lane",
    "actions": ""
  },
  {
    "id": 464,
    "firstname": "Hillery",
    "last_name": "Wildin",
    "email": "hwildincv@wsj.com",
    "address": "23 Reinke Place",
    "actions": ""
  },
  {
    "id": 465,
    "firstname": "Arin",
    "last_name": "Rannigan",
    "email": "arannigancw@seattletimes.com",
    "address": "0669 Grasskamp Place",
    "actions": ""
  },
  {
    "id": 466,
    "firstname": "Diandra",
    "last_name": "Frammingham",
    "email": "dframminghamcx@hud.gov",
    "address": "82 Northwestern Point",
    "actions": ""
  },
  {
    "id": 467,
    "firstname": "Marlie",
    "last_name": "Wyman",
    "email": "mwymancy@addtoany.com",
    "address": "05 School Way",
    "actions": ""
  },
  {
    "id": 468,
    "firstname": "Davida",
    "last_name": "Culham",
    "email": "dculhamcz@wisc.edu",
    "address": "1 Mallard Pass",
    "actions": ""
  },
  {
    "id": 469,
    "firstname": "Jarret",
    "last_name": "Bumphries",
    "email": "jbumphriesd0@deviantart.com",
    "address": "14 Clyde Gallagher Park",
    "actions": ""
  },
  {
    "id": 470,
    "firstname": "Jourdain",
    "last_name": "Hannis",
    "email": "jhannisd1@go.com",
    "address": "0 Claremont Way",
    "actions": ""
  },
  {
    "id": 471,
    "firstname": "Saundra",
    "last_name": "Digman",
    "email": "sdigmand2@tamu.edu",
    "address": "77768 Golden Leaf Terrace",
    "actions": ""
  },
  {
    "id": 472,
    "firstname": "Tammi",
    "last_name": "Toppas",
    "email": "ttoppasd3@cargocollective.com",
    "address": "927 Moulton Road",
    "actions": ""
  },
  {
    "id": 473,
    "firstname": "Angelia",
    "last_name": "Barke",
    "email": "abarked4@a8.net",
    "address": "8111 Hanover Hill",
    "actions": ""
  },
  {
    "id": 474,
    "firstname": "Desi",
    "last_name": "Maasze",
    "email": "dmaaszed5@sfgate.com",
    "address": "3912 Tennyson Court",
    "actions": ""
  },
  {
    "id": 475,
    "firstname": "Miles",
    "last_name": "Goldspink",
    "email": "mgoldspinkd6@adobe.com",
    "address": "89 Sutteridge Alley",
    "actions": ""
  },
  {
    "id": 476,
    "firstname": "Veradis",
    "last_name": "Rosbottom",
    "email": "vrosbottomd7@dedecms.com",
    "address": "6 Green Ridge Terrace",
    "actions": ""
  },
  {
    "id": 477,
    "firstname": "Ranique",
    "last_name": "Styche",
    "email": "rstyched8@people.com.cn",
    "address": "14 Hovde Trail",
    "actions": ""
  },
  {
    "id": 478,
    "firstname": "Evelyn",
    "last_name": "Hellens",
    "email": "ehellensd9@webs.com",
    "address": "0 Grasskamp Hill",
    "actions": ""
  },
  {
    "id": 479,
    "firstname": "Wenonah",
    "last_name": "Crush",
    "email": "wcrushda@liveinternet.ru",
    "address": "900 Columbus Place",
    "actions": ""
  },
  {
    "id": 480,
    "firstname": "Zelma",
    "last_name": "Hassen",
    "email": "zhassendb@virginia.edu",
    "address": "9 Carey Circle",
    "actions": ""
  },
  {
    "id": 481,
    "firstname": "Ainsley",
    "last_name": "Terbrugge",
    "email": "aterbruggedc@blogtalkradio.com",
    "address": "1 Jana Center",
    "actions": ""
  },
  {
    "id": 482,
    "firstname": "Eliza",
    "last_name": "Lettsom",
    "email": "elettsomdd@amazon.co.uk",
    "address": "02052 Dayton Parkway",
    "actions": ""
  },
  {
    "id": 483,
    "firstname": "Valli",
    "last_name": "Bowler",
    "email": "vbowlerde@sakura.ne.jp",
    "address": "021 Norway Maple Court",
    "actions": ""
  },
  {
    "id": 484,
    "firstname": "Andrej",
    "last_name": "Meakin",
    "email": "ameakindf@smugmug.com",
    "address": "27211 School Parkway",
    "actions": ""
  },
  {
    "id": 485,
    "firstname": "Duncan",
    "last_name": "Kalkhoven",
    "email": "dkalkhovendg@comsenz.com",
    "address": "3 Spaight Center",
    "actions": ""
  },
  {
    "id": 486,
    "firstname": "Emelyne",
    "last_name": "Stirley",
    "email": "estirleydh@seesaa.net",
    "address": "7 Victoria Pass",
    "actions": ""
  },
  {
    "id": 487,
    "firstname": "Aurlie",
    "last_name": "Rebichon",
    "email": "arebichondi@ed.gov",
    "address": "10116 Shasta Road",
    "actions": ""
  },
  {
    "id": 488,
    "firstname": "Lona",
    "last_name": "Foyster",
    "email": "lfoysterdj@google.nl",
    "address": "99077 Annamark Park",
    "actions": ""
  },
  {
    "id": 489,
    "firstname": "Eric",
    "last_name": "Abrehart",
    "email": "eabrehartdk@wordpress.com",
    "address": "5 Hallows Avenue",
    "actions": ""
  },
  {
    "id": 490,
    "firstname": "Agace",
    "last_name": "Prestie",
    "email": "aprestiedl@blogtalkradio.com",
    "address": "7753 Parkside Junction",
    "actions": ""
  },
  {
    "id": 491,
    "firstname": "Austin",
    "last_name": "Stockle",
    "email": "astockledm@wisc.edu",
    "address": "5 Dapin Terrace",
    "actions": ""
  },
  {
    "id": 492,
    "firstname": "Vivienne",
    "last_name": "Celiz",
    "email": "vcelizdn@forbes.com",
    "address": "37 Toban Alley",
    "actions": ""
  },
  {
    "id": 493,
    "firstname": "Marshal",
    "last_name": "Raxworthy",
    "email": "mraxworthydo@cdbaby.com",
    "address": "4 Rieder Center",
    "actions": ""
  },
  {
    "id": 494,
    "firstname": "Gerry",
    "last_name": "Symondson",
    "email": "gsymondsondp@lulu.com",
    "address": "2651 Petterle Point",
    "actions": ""
  },
  {
    "id": 495,
    "firstname": "Morton",
    "last_name": "Gatheridge",
    "email": "mgatheridgedq@disqus.com",
    "address": "065 Crownhardt Court",
    "actions": ""
  },
  {
    "id": 496,
    "firstname": "Roch",
    "last_name": "Gremain",
    "email": "rgremaindr@cargocollective.com",
    "address": "16 Erie Avenue",
    "actions": ""
  },
  {
    "id": 497,
    "firstname": "Tiffanie",
    "last_name": "Doel",
    "email": "tdoelds@goo.ne.jp",
    "address": "2 Nobel Terrace",
    "actions": ""
  },
  {
    "id": 498,
    "firstname": "Ketty",
    "last_name": "Tripney",
    "email": "ktripneydt@cbslocal.com",
    "address": "82 Jackson Park",
    "actions": ""
  },
  {
    "id": 499,
    "firstname": "Salli",
    "last_name": "Whinney",
    "email": "swhinneydu@goodreads.com",
    "address": "687 Portage Place",
    "actions": ""
  },
  {
    "id": 500,
    "firstname": "Jonas",
    "last_name": "Jemmett",
    "email": "jjemmettdv@weebly.com",
    "address": "956 Fisk Hill",
    "actions": ""
  }
]
